{"viewId":1631427984798,"height":2000,"width":2000,"backgroundOverlayColor":"#00000000","backgroundColor":"#FFFFFFFF","version":9,"subViews":[{"viewId":1631507819771,"layerFullLocked":true,"layerHidden":false,"layerLocked":"false","maskRoundRectRadius":0,"border":"0","borderColor":"#00000000","borderDash":0,"borderDashGap":0,"borderStyle":0,"opacity":"1.0","rotateAngle":"90.0","backgroundColor":"#00000000","xPoint":"0.0","yPoint":"0.0","selected":"false","tiltX":0,"tiltY":0,"layoutParamsHeight":"-1","layoutParamsWidth":"-1","rootLayoutHeight":"2000","rootLayoutWidth":"2000","textPadding":0,"viewType":"shapeView2","zoomScale":"0.7200001","shapeLayers":[{"shapeType":"shapePolygon","shapeVertices":[{"xPoint":855.013427734375,"yPoint":192.92205810546875,"shapeBezChanged":false,"shapeVertBezPrev":{"xPoint":717.4228515625,"yPoint":270.74188232421875,"shapeBezChanged":true},"shapeVertBezNext":{"xPoint":904.33935546875,"yPoint":167.79891967773438,"shapeBezChanged":false}},{"xPoint":1003.006591796875,"yPoint":117.54496765136719,"shapeBezChanged":false,"shapeVertBezPrev":{"xPoint":953.680419921875,"yPoint":142.66806030273438,"shapeBezChanged":false},"shapeVertBezNext":{"xPoint":1049.144287109375,"yPoint":142.73745727539062,"shapeBezChanged":false}},{"xPoint":1141.4346923828125,"yPoint":193.13031005859375,"shapeBezChanged":false,"shapeVertBezPrev":{"xPoint":1095.296142578125,"yPoint":167.9376678466797,"shapeBezChanged":false},"shapeVertBezNext":{"xPoint":1383.4222412109375,"yPoint":317.2529296875,"shapeBezChanged":true}},{"xPoint":1620.8233642578125,"yPoint":661.7193603515625,"shapeBezChanged":false,"shapeVertBezPrev":{"xPoint":1632.956787109375,"yPoint":374.6988830566406,"shapeBezChanged":true},"shapeVertBezNext":{"xPoint":1618.3062744140625,"yPoint":742.8087768554688,"shapeBezChanged":true}},{"xPoint":1727.15869140625,"yPoint":783.4287109375,"shapeBezChanged":false,"shapeVertBezPrev":{"xPoint":1691.7174072265625,"yPoint":742.8630981445312,"shapeBezChanged":false},"shapeVertBezNext":{"xPoint":1727.26953125,"yPoint":796.9312133789062,"shapeBezChanged":false}},{"xPoint":1727.4912109375,"yPoint":823.9400024414062,"shapeBezChanged":false,"shapeVertBezPrev":{"xPoint":1727.380859375,"yPoint":810.4374389648438,"shapeBezChanged":false},"shapeVertBezNext":{"xPoint":1832.6502685546875,"yPoint":823.8318481445312,"shapeBezChanged":false}},{"xPoint":2043,"yPoint":823.6162109375,"shapeBezChanged":false,"shapeVertBezPrev":{"xPoint":1937.8408203125,"yPoint":823.7242431640625,"shapeBezChanged":false},"shapeVertBezNext":{"xPoint":2042.885498046875,"yPoint":528.7736206054688,"shapeBezChanged":false}},{"xPoint":2042.6552734375,"yPoint":-61,"shapeBezChanged":false,"shapeVertBezPrev":{"xPoint":2042.770263671875,"yPoint":233.8427734375,"shapeBezChanged":false},"shapeVertBezNext":{"xPoint":1347.83984375,"yPoint":-60.777366638183594,"shapeBezChanged":false}},{"xPoint":-42,"yPoint":-60.331809997558594,"shapeBezChanged":false,"shapeVertBezPrev":{"xPoint":652.8155517578125,"yPoint":-60.55458450317383,"shapeBezChanged":false},"shapeVertBezNext":{"xPoint":-42,"yPoint":234.28799438476562,"shapeBezChanged":false}},{"xPoint":-42,"yPoint":823.6162109375,"shapeBezChanged":false,"shapeVertBezPrev":{"xPoint":-42,"yPoint":528.996337890625,"shapeBezChanged":false},"shapeVertBezNext":{"xPoint":64.37484741210938,"yPoint":823.6162109375,"shapeBezChanged":false}},{"xPoint":277.1564636230469,"yPoint":823.6162109375,"shapeBezChanged":false,"shapeVertBezPrev":{"xPoint":170.78167724609375,"yPoint":823.6162109375,"shapeBezChanged":false},"shapeVertBezNext":{"xPoint":277.1564636230469,"yPoint":810.221435546875,"shapeBezChanged":false}},{"xPoint":277.1564636230469,"yPoint":783.4287109375,"shapeBezChanged":false,"shapeVertBezPrev":{"xPoint":277.1564636230469,"yPoint":796.8237915039062,"shapeBezChanged":false},"shapeVertBezNext":{"xPoint":375.8885498046875,"yPoint":732.7621459960938,"shapeBezChanged":true}},{"xPoint":388.18804931640625,"yPoint":662.6959838867188,"shapeBezChanged":false,"shapeVertBezPrev":{"xPoint":394.850830078125,"yPoint":703.4563598632812,"shapeBezChanged":true},"shapeVertBezNext":{"xPoint":386.7142333984375,"yPoint":360.56866455078125,"shapeBezChanged":true}}],"shapeVerticesVer":1,"fillColor":"#00FF0000","borderColor":"#FF3B1F43","border":78,"joinType":1,"rotateAngle":0,"cornerRadius":0,"borderDash":0,"borderDashGap":0,"borderStyle":0,"shadow":{"shadowRadius":0,"shadowColor":"#FF444444","shadowDist":15,"shadowAngle":45}}],"flipHorizontal":1,"flipVertical":1},{"viewId":1631508215518,"layerFullLocked":true,"layerHidden":false,"layerLocked":"false","maskRoundRectRadius":0,"border":"0","borderColor":"#00000000","borderDash":0,"borderDashGap":0,"borderStyle":0,"opacity":"1.0","rotateAngle":"90.0","backgroundColor":"#00000000","xPoint":"0.0","yPoint":"0.0","selected":"false","tiltX":0,"tiltY":0,"layoutParamsHeight":"-1","layoutParamsWidth":"-1","rootLayoutHeight":"2000","rootLayoutWidth":"2000","textPadding":0,"viewType":"shapeView2","zoomScale":"0.7200001","shapeLayers":[{"shapeType":"shapePolygon","shapeVertices":[{"xPoint":855.013427734375,"yPoint":193.80628967285156,"shapeBezChanged":false,"shapeVertBezPrev":{"xPoint":717.4228515625,"yPoint":271.8970031738281,"shapeBezChanged":true},"shapeVertBezNext":{"xPoint":904.33935546875,"yPoint":168.59561157226562,"shapeBezChanged":false}},{"xPoint":1003.006591796875,"yPoint":118.16673278808594,"shapeBezChanged":false,"shapeVertBezPrev":{"xPoint":953.680419921875,"yPoint":143.3773193359375,"shapeBezChanged":false},"shapeVertBezNext":{"xPoint":1049.144287109375,"yPoint":143.44679260253906,"shapeBezChanged":false}},{"xPoint":1141.4346923828125,"yPoint":194.01512145996094,"shapeBezChanged":false,"shapeVertBezPrev":{"xPoint":1095.296142578125,"yPoint":168.7348175048828,"shapeBezChanged":false},"shapeVertBezNext":{"xPoint":1383.4222412109375,"yPoint":318.5699768066406,"shapeBezChanged":true}},{"xPoint":1620.8233642578125,"yPoint":664.2359619140625,"shapeBezChanged":false,"shapeVertBezPrev":{"xPoint":1632.956787109375,"yPoint":376.21600341796875,"shapeBezChanged":true},"shapeVertBezNext":{"xPoint":1618.3062744140625,"yPoint":745.6075439453125,"shapeBezChanged":true}},{"xPoint":1727.15869140625,"yPoint":786.369140625,"shapeBezChanged":false,"shapeVertBezPrev":{"xPoint":1691.7174072265625,"yPoint":745.662353515625,"shapeBezChanged":false},"shapeVertBezNext":{"xPoint":1727.26953125,"yPoint":799.9185180664062,"shapeBezChanged":false}},{"xPoint":1727.4912109375,"yPoint":827.0216674804688,"shapeBezChanged":false,"shapeVertBezPrev":{"xPoint":1727.380859375,"yPoint":813.4721069335938,"shapeBezChanged":false},"shapeVertBezNext":{"xPoint":1832.6502685546875,"yPoint":826.913330078125,"shapeBezChanged":false}},{"xPoint":2043,"yPoint":826.6963500976562,"shapeBezChanged":false,"shapeVertBezPrev":{"xPoint":1937.8408203125,"yPoint":826.8050537109375,"shapeBezChanged":false},"shapeVertBezNext":{"xPoint":2042.885498046875,"yPoint":530.8273315429688,"shapeBezChanged":false}},{"xPoint":2042.6552734375,"yPoint":-61,"shapeBezChanged":false,"shapeVertBezPrev":{"xPoint":2042.770263671875,"yPoint":234.86932373046875,"shapeBezChanged":false},"shapeVertBezNext":{"xPoint":1347.83984375,"yPoint":-60.77657699584961,"shapeBezChanged":false}},{"xPoint":-42,"yPoint":-60.32950210571289,"shapeBezChanged":false,"shapeVertBezPrev":{"xPoint":652.8155517578125,"yPoint":-60.55304718017578,"shapeBezChanged":false},"shapeVertBezNext":{"xPoint":-42,"yPoint":235.31625366210938,"shapeBezChanged":false}},{"xPoint":-42,"yPoint":826.6963500976562,"shapeBezChanged":false,"shapeVertBezPrev":{"xPoint":-42,"yPoint":531.0506591796875,"shapeBezChanged":false},"shapeVertBezNext":{"xPoint":64.37484741210938,"yPoint":826.6963500976562,"shapeBezChanged":false}},{"xPoint":277.1564636230469,"yPoint":826.6963500976562,"shapeBezChanged":false,"shapeVertBezPrev":{"xPoint":170.78167724609375,"yPoint":826.6963500976562,"shapeBezChanged":false},"shapeVertBezNext":{"xPoint":277.1564636230469,"yPoint":813.2554931640625,"shapeBezChanged":false}},{"xPoint":277.1564636230469,"yPoint":786.369140625,"shapeBezChanged":false,"shapeVertBezPrev":{"xPoint":277.1564636230469,"yPoint":799.8104248046875,"shapeBezChanged":false},"shapeVertBezNext":{"xPoint":375.8885498046875,"yPoint":735.526123046875,"shapeBezChanged":true}},{"xPoint":388.18804931640625,"yPoint":665.2164916992188,"shapeBezChanged":false,"shapeVertBezPrev":{"xPoint":394.850830078125,"yPoint":706.1182250976562,"shapeBezChanged":true},"shapeVertBezNext":{"xPoint":386.7142333984375,"yPoint":362.03668212890625,"shapeBezChanged":true}}],"shapeVerticesVer":1,"fillColor":"#00FF0000","borderColor":"#FF8E49A1","border":28,"joinType":1,"rotateAngle":0,"cornerRadius":0,"borderDash":0,"borderDashGap":0,"borderStyle":0,"shadow":{"shadowRadius":0,"shadowColor":"#FF444444","shadowDist":15,"shadowAngle":45}}],"flipHorizontal":1,"flipVertical":1},{"viewId":1631507758540,"layerFullLocked":true,"layerHidden":false,"layerLocked":"false","maskRoundRectRadius":0,"border":"0","borderColor":"#00000000","borderDash":0,"borderDashGap":0,"borderStyle":0,"opacity":"1.0","rotateAngle":"90.0","backgroundColor":"#00000000","xPoint":"0.0","yPoint":"0.0","selected":"false","tiltX":0,"tiltY":0,"layoutParamsHeight":"-1","layoutParamsWidth":"-1","rootLayoutHeight":"2000","rootLayoutWidth":"2000","textPadding":0,"viewType":"shapeView2","zoomScale":"0.7200001","shapeLayers":[{"shapeType":"shapePolygon","shapeVertices":[{"xPoint":861,"yPoint":111.77577209472656,"shapeBezChanged":false,"shapeVertBezPrev":{"xPoint":678.5941162109375,"yPoint":223.41444396972656,"shapeBezChanged":true},"shapeVertBezNext":{"xPoint":908.1299438476562,"yPoint":87.33995056152344,"shapeBezChanged":false}},{"xPoint":1002.4039916992188,"yPoint":38.46095275878906,"shapeBezChanged":false,"shapeVertBezPrev":{"xPoint":955.2740478515625,"yPoint":62.89679718017578,"shapeBezChanged":false},"shapeVertBezNext":{"xPoint":1046.6612548828125,"yPoint":63.23323059082031,"shapeBezChanged":false}},{"xPoint":1135.18896484375,"yPoint":112.7851791381836,"shapeBezChanged":false,"shapeVertBezPrev":{"xPoint":1090.9317626953125,"yPoint":88.01295471191406,"shapeBezChanged":false},"shapeVertBezNext":{"xPoint":1367.311279296875,"yPoint":234.8368377685547,"shapeBezChanged":true}},{"xPoint":1670,"yPoint":630.0088500976562,"shapeBezChanged":false,"shapeVertBezPrev":{"xPoint":1681.638427734375,"yPoint":347.77703857421875,"shapeBezChanged":true},"shapeVertBezNext":{"xPoint":1667.5850830078125,"yPoint":709.7450561523438,"shapeBezChanged":true}},{"xPoint":1772,"yPoint":735.0101928710938,"shapeBezChanged":false,"shapeVertBezPrev":{"xPoint":1738.00341796875,"yPoint":700.0133666992188,"shapeBezChanged":false},"shapeVertBezNext":{"xPoint":1772,"yPoint":743.2890014648438,"shapeBezChanged":false}},{"xPoint":1772,"yPoint":759.8492431640625,"shapeBezChanged":false,"shapeVertBezPrev":{"xPoint":1772,"yPoint":751.5704956054688,"shapeBezChanged":false},"shapeVertBezNext":{"xPoint":1847.992431640625,"yPoint":759.8492431640625,"shapeBezChanged":false}},{"xPoint":2000,"yPoint":759.8492431640625,"shapeBezChanged":false,"shapeVertBezPrev":{"xPoint":1924.007568359375,"yPoint":759.8492431640625,"shapeBezChanged":false},"shapeVertBezNext":{"xPoint":2000,"yPoint":506.5914611816406,"shapeBezChanged":false}},{"xPoint":2000,"yPoint":0,"shapeBezChanged":false,"shapeVertBezPrev":{"xPoint":2000,"yPoint":253.25775146484375,"shapeBezChanged":false},"shapeVertBezNext":{"xPoint":1333.4000244140625,"yPoint":0,"shapeBezChanged":false}},{"xPoint":0,"yPoint":0,"shapeBezChanged":false,"shapeVertBezPrev":{"xPoint":666.5999755859375,"yPoint":0,"shapeBezChanged":false},"shapeVertBezNext":{"xPoint":0,"yPoint":253.3380126953125,"shapeBezChanged":false}},{"xPoint":0,"yPoint":760.0900268554688,"shapeBezChanged":false,"shapeVertBezPrev":{"xPoint":0,"yPoint":506.75201416015625,"shapeBezChanged":false},"shapeVertBezNext":{"xPoint":76.32569885253906,"yPoint":760.0900268554688,"shapeBezChanged":false}},{"xPoint":229,"yPoint":760.0900268554688,"shapeBezChanged":false,"shapeVertBezPrev":{"xPoint":152.67430114746094,"yPoint":760.0900268554688,"shapeBezChanged":false},"shapeVertBezNext":{"xPoint":229,"yPoint":751.7980346679688,"shapeBezChanged":false}},{"xPoint":229,"yPoint":735.21142578125,"shapeBezChanged":false,"shapeVertBezPrev":{"xPoint":229,"yPoint":743.5036010742188,"shapeBezChanged":false},"shapeVertBezNext":{"xPoint":323.70709228515625,"yPoint":685.389892578125,"shapeBezChanged":true}},{"xPoint":335.5052795410156,"yPoint":630.5139770507812,"shapeBezChanged":false,"shapeVertBezPrev":{"xPoint":341.896240234375,"yPoint":670.5948486328125,"shapeBezChanged":true},"shapeVertBezNext":{"xPoint":334.091552734375,"yPoint":333.42724609375,"shapeBezChanged":true}}],"shapeVerticesVer":1,"fillColor":"#FF5B2F67","borderColor":"#FFFFFFFF","border":0,"joinType":1,"rotateAngle":0,"cornerRadius":0,"borderDash":0,"borderDashGap":0,"borderStyle":0,"gradient":{"angle":90,"colors":["#FF5B2F67","#FF804291","#FF804291"],"type":0,"grWidth":0,"grHeight":0},"shadow":{"shadowRadius":0,"shadowColor":"#FF444444","shadowDist":15,"shadowAngle":45}}],"flipHorizontal":1,"flipVertical":1},{"viewId":1632452482582,"layerFullLocked":true,"layerHidden":false,"layerLocked":"false","maskRoundRectRadius":0,"border":"0","borderColor":"#00000000","borderDash":0,"borderDashGap":0,"borderStyle":0,"opacity":"1.0","rotateAngle":"90.0","backgroundColor":"#00000000","xPoint":"0.0","yPoint":"0.0","selected":"false","tiltX":0,"tiltY":0,"layoutParamsHeight":"-1","layoutParamsWidth":"-1","rootLayoutHeight":"2000","rootLayoutWidth":"2000","textPadding":0,"viewType":"shapeView2","zoomScale":"0.7200001","shapeLayers":[{"shapeType":"shapePolygon","shapeVertices":[{"xPoint":-452,"yPoint":2024.018798828125,"shapeBezChanged":false,"shapeVertBezPrev":{"xPoint":-452,"yPoint":1969.3515625,"shapeBezChanged":false},"shapeVertBezNext":{"xPoint":516.3797607421875,"yPoint":2024.018798828125,"shapeBezChanged":false}},{"xPoint":2453.4296875,"yPoint":2024.018798828125,"shapeBezChanged":false,"shapeVertBezPrev":{"xPoint":1485.0494384765625,"yPoint":2024.018798828125,"shapeBezChanged":false},"shapeVertBezNext":{"xPoint":2453.4296875,"yPoint":1969.3515625,"shapeBezChanged":false}},{"xPoint":2453.4296875,"yPoint":1860,"shapeBezChanged":false,"shapeVertBezPrev":{"xPoint":2453.4296875,"yPoint":1914.667236328125,"shapeBezChanged":false},"shapeVertBezNext":{"xPoint":1485.0494384765625,"yPoint":1860,"shapeBezChanged":false}},{"xPoint":-452,"yPoint":1860,"shapeBezChanged":false,"shapeVertBezPrev":{"xPoint":516.3797607421875,"yPoint":1860,"shapeBezChanged":false},"shapeVertBezNext":{"xPoint":-452,"yPoint":1914.667236328125,"shapeBezChanged":false}}],"shapeVerticesVer":1,"fillColor":"#FF8E49A1","borderColor":"#FF3B1F43","border":20,"joinType":1,"rotateAngle":0,"cornerRadius":0,"borderDash":0,"borderDashGap":0,"borderStyle":0,"shadow":{"shadowRadius":0,"shadowColor":"#FF444444","shadowDist":15,"shadowAngle":45}}],"flipHorizontal":1,"flipVertical":1},{"viewId":1618509483713,"layerFullLocked":false,"layerHidden":false,"layerLocked":"true","maskRoundRectRadius":26,"border":"0","borderColor":"#00000000","borderDash":0,"borderDashGap":0,"borderStyle":0,"opacity":"1.0","rotateAngle":"90.0","backgroundColor":"#00000000","xPoint":"1478.7296","yPoint":"1875.7855","selected":"false","tiltX":0,"tiltY":0,"layoutParamsHeight":"-2","layoutParamsWidth":"-2","rootLayoutHeight":"66","rootLayoutWidth":"66","textPadding":0,"viewType":"shapeView","zoomScale":"0.7200001","text":"Q","textAlignment":"textCenterAlignment","textVerticalAlignment":"textCenterVerticalAlignment","typeFaceName":"social_media.otf","typeFaceType":"icon","typeFaceLang":"","textSize":"0.0","textSizeSP":0,"textColor":"#FFFFFFFF","flipHorizontal":"1.0","flipVertical":"1.0","stroke":"0.0","strokeColor":"#FF696969","shadowRadius":"0.0","shadowThickness":"#00000001","shadowColor":"#FF444444","shadowX":"5.0","shadowY":"5.0","lineSpacing":"1.0","wordSpacing":0.0010000000474974513,"wordArc":0,"textBold":false,"textItalic":false,"textUnderline":false,"textEmboss":false,"textEmbossFull":false,"zeroSpans":[],"harfSpans":[],"textDirection":1,"textTextureScale":0,"projectName":"project_1632947218126","shapeViewVer":2},{"viewId":1618509682343,"layerFullLocked":false,"layerHidden":false,"layerLocked":"true","maskRoundRectRadius":26,"border":"0","borderColor":"#00000000","borderDash":0,"borderDashGap":0,"borderStyle":0,"opacity":"1.0","rotateAngle":"90.0","backgroundColor":"#00000000","xPoint":"51.0","yPoint":"1875.7855","selected":"false","tiltX":0,"tiltY":0,"layoutParamsHeight":"-2","layoutParamsWidth":"-2","rootLayoutHeight":"66","rootLayoutWidth":"66","textPadding":0,"viewType":"shapeView","zoomScale":"0.7200001","text":"D","textAlignment":"textCenterAlignment","textVerticalAlignment":"textCenterVerticalAlignment","typeFaceName":"social_media.otf","typeFaceType":"icon","typeFaceLang":"","textSize":"0.0","textSizeSP":0,"textColor":"#FFFFFFFF","flipHorizontal":"1.0","flipVertical":"1.0","stroke":"0.0","strokeColor":"#FF696969","shadowRadius":"0.0","shadowThickness":"#00000001","shadowColor":"#FF444444","shadowX":"5.0","shadowY":"5.0","lineSpacing":"1.0","wordSpacing":0.0010000000474974513,"wordArc":0,"textBold":false,"textItalic":false,"textUnderline":false,"textEmboss":false,"textEmbossFull":false,"zeroSpans":[],"harfSpans":[],"textDirection":1,"textTextureScale":0,"projectName":"project_1632947218126","shapeViewVer":2},{"viewId":1618509688339,"layerFullLocked":false,"layerHidden":false,"layerLocked":"true","maskRoundRectRadius":26,"border":"0","borderColor":"#00000000","borderDash":0,"borderDashGap":0,"borderStyle":0,"opacity":"1.0","rotateAngle":"90.0","backgroundColor":"#00000000","xPoint":"797.4192","yPoint":"1875.7855","selected":"false","tiltX":0,"tiltY":0,"layoutParamsHeight":"-2","layoutParamsWidth":"-2","rootLayoutHeight":"66","rootLayoutWidth":"66","textPadding":0,"viewType":"shapeView","zoomScale":"0.7200001","text":"E","textAlignment":"textCenterAlignment","textVerticalAlignment":"textCenterVerticalAlignment","typeFaceName":"social_media.otf","typeFaceType":"icon","typeFaceLang":"","textSize":"0.0","textSizeSP":0,"textColor":"#FFFFFFFF","flipHorizontal":"1.0","flipVertical":"1.0","stroke":"0.0","strokeColor":"#FF696969","shadowRadius":"0.0","shadowThickness":"#00000001","shadowColor":"#FF444444","shadowX":"5.0","shadowY":"5.0","lineSpacing":"1.0","wordSpacing":0.0010000000474974513,"wordArc":0,"textBold":false,"textItalic":false,"textUnderline":false,"textEmboss":false,"textEmbossFull":false,"zeroSpans":[],"harfSpans":[],"textDirection":1,"textTextureScale":0,"projectName":"project_1632947218126","shapeViewVer":2},{"viewId":1618509528573,"layerFullLocked":false,"layerHidden":false,"layerLocked":"true","maskRoundRectRadius":26,"border":"0","borderColor":"#00000000","borderDash":0,"borderDashGap":0,"borderStyle":0,"opacity":"1.0","rotateAngle":"90.0","backgroundColor":"#00000000","xPoint":"1559.902","yPoint":"1863.8887","selected":"false","tiltX":0,"tiltY":0,"layoutParamsHeight":"-2","layoutParamsWidth":"-2","rootLayoutHeight":"109","rootLayoutWidth":"390","textPadding":0,"viewType":"textView","zoomScale":"0.7200001","text":"IMAGITOR","textAlignment":"textLeftAlignment","textVerticalAlignment":"textTopAlignment","typeFaceName":"Roboto-Regular","typeFaceType":"all","typeFaceLang":"","textSize":"19.428572","textSizeSP":68,"textColor":"#FFFFFFFF","flipHorizontal":"1.0","flipVertical":"1.0","stroke":"0.0","strokeColor":"#FF696969","shadowRadius":"0.0","shadowThickness":"#00000001","shadowColor":"#FF444444","shadowX":"5.0","shadowY":"5.0","lineSpacing":"1.0","wordSpacing":0.0010000000474974513,"wordArc":0,"textBold":false,"textItalic":false,"textUnderline":false,"textEmboss":false,"textEmbossFull":false,"zeroSpans":[],"harfSpans":[],"textDirection":1,"textTextureScale":0,"projectName":"project_1632947218126"},{"viewId":1618509682365,"layerFullLocked":false,"layerHidden":false,"layerLocked":"true","maskRoundRectRadius":26,"border":"0","borderColor":"#00000000","borderDash":0,"borderDashGap":0,"borderStyle":0,"opacity":"1.0","rotateAngle":"90.0","backgroundColor":"#00000000","xPoint":"132.38522","yPoint":"1863.8887","selected":"false","tiltX":0,"tiltY":0,"layoutParamsHeight":"-2","layoutParamsWidth":"-2","rootLayoutHeight":"109","rootLayoutWidth":"390","textPadding":0,"viewType":"textView","zoomScale":"0.7200001","text":"IMAGITOR","textAlignment":"textLeftAlignment","textVerticalAlignment":"textTopAlignment","typeFaceName":"Roboto-Regular","typeFaceType":"all","typeFaceLang":"","textSize":"19.428572","textSizeSP":68,"textColor":"#FFFFFFFF","flipHorizontal":"1.0","flipVertical":"1.0","stroke":"0.0","strokeColor":"#FF696969","shadowRadius":"0.0","shadowThickness":"#00000001","shadowColor":"#FF444444","shadowX":"5.0","shadowY":"5.0","lineSpacing":"1.0","wordSpacing":0.0010000000474974513,"wordArc":0,"textBold":false,"textItalic":false,"textUnderline":false,"textEmboss":false,"textEmbossFull":false,"zeroSpans":[],"harfSpans":[],"textDirection":1,"textTextureScale":0,"projectName":"project_1632947218126"},{"viewId":1618509688354,"layerFullLocked":false,"layerHidden":false,"layerLocked":"true","maskRoundRectRadius":26,"border":"0","borderColor":"#00000000","borderDash":0,"borderDashGap":0,"borderStyle":0,"opacity":"1.0","rotateAngle":"90.0","backgroundColor":"#00000000","xPoint":"878.8043","yPoint":"1863.8887","selected":"false","tiltX":0,"tiltY":0,"layoutParamsHeight":"-2","layoutParamsWidth":"-2","rootLayoutHeight":"109","rootLayoutWidth":"390","textPadding":0,"viewType":"textView","zoomScale":"0.7200001","text":"IMAGITOR","textAlignment":"textLeftAlignment","textVerticalAlignment":"textTopAlignment","typeFaceName":"Roboto-Regular","typeFaceType":"all","typeFaceLang":"","textSize":"19.428572","textSizeSP":68,"textColor":"#FFFFFFFF","flipHorizontal":"1.0","flipVertical":"1.0","stroke":"0.0","strokeColor":"#FF696969","shadowRadius":"0.0","shadowThickness":"#00000001","shadowColor":"#FF444444","shadowX":"5.0","shadowY":"5.0","lineSpacing":"1.0","wordSpacing":0.0010000000474974513,"wordArc":0,"textBold":false,"textItalic":false,"textUnderline":false,"textEmboss":false,"textEmbossFull":false,"zeroSpans":[],"harfSpans":[],"textDirection":1,"textTextureScale":0,"projectName":"project_1632947218126"},{"viewId":1632637826695,"layerFullLocked":false,"layerHidden":false,"layerLocked":"false","maskRoundRectRadius":30,"border":"0","borderColor":"#00000000","borderDash":0,"borderDashGap":0,"borderStyle":0,"opacity":"1.0","rotateAngle":"90.0","backgroundColor":"#00000000","xPoint":"97.22221","yPoint":"981.1111","selected":"false","tiltX":0,"tiltY":0,"layoutParamsHeight":"-2","layoutParamsWidth":"-2","rootLayoutHeight":"668","rootLayoutWidth":"1802","textPadding":0,"viewType":"textView","zoomScale":"0.7200001","text":"اللہ کی رضا کے لیے دن بھر روزے رکھنا اور رات بھر نماز پڑھنا یقیناً یہ دونوں بہت بڑے اعمال ہیں اور انسان ان سے بہت بلند درجہ حاصل کرلیتا ہے۔ آپ ﷺ نے اخلاق عالیہ کی فضیلت بیان کرتے ہوۓ فرمایا کہ یہی درجہ انسان اچھے اخلاق سے بھی حاصل کر سکتا ہے۔","textAlignment":"textCenterAlignment","textVerticalAlignment":"textTopAlignment","typeFaceName":"Mehr Nastaliq Web","typeFaceType":"urdu","typeFaceLang":"","textSize":"27.428572","textSizeSP":96,"textColor":"#FF000428","flipHorizontal":"1.0","flipVertical":"1.0","stroke":"0.0","strokeColor":"#FF696969","shadowRadius":"0.0","shadowThickness":"#00000001","shadowColor":"#FF444444","shadowX":"5.0","shadowY":"5.0","lineSpacing":"1.0","wordSpacing":0.0010000000474974513,"wordArc":0,"textBold":false,"textItalic":false,"textUnderline":false,"textEmboss":false,"textEmbossFull":false,"zeroSpans":[],"harfSpans":[],"textDirection":1,"textTextureScale":0,"projectName":"project_1632947218126"},{"viewId":1632637841287,"layerFullLocked":false,"layerHidden":false,"layerLocked":"true","maskRoundRectRadius":30,"border":"0","borderColor":"#00000000","borderDash":0,"borderDashGap":0,"borderStyle":0,"opacity":"1.0","rotateAngle":"90.0","backgroundColor":"#00000000","xPoint":"73.0","yPoint":"1666.6665","selected":"false","tiltX":0,"tiltY":0,"layoutParamsHeight":"-2","layoutParamsWidth":"-2","rootLayoutHeight":"140","rootLayoutWidth":"899","textPadding":0,"viewType":"textView","zoomScale":"0.7200001","text":"﴿ترمذی شریف،2003﴾","textAlignment":"textCenterAlignment","textVerticalAlignment":"textTopAlignment","typeFaceName":"qadree-regular","typeFaceType":"urdu","typeFaceLang":"urdu","textSize":"22.285715","textSizeSP":78,"textColor":"#FF000428","flipHorizontal":"1.0","flipVertical":"1.0","stroke":"0.0","strokeColor":"#FF696969","shadowRadius":"0.0","shadowThickness":"#00000001","shadowColor":"#FF444444","shadowX":"5.0","shadowY":"5.0","lineSpacing":"1.0","wordSpacing":0.0010000000474974513,"wordArc":0,"textBold":false,"textItalic":false,"textUnderline":false,"textEmboss":false,"textEmbossFull":false,"zeroSpans":[],"harfSpans":[],"textDirection":1,"textTextureScale":0,"projectName":"project_1632947218126"},{"viewId":1632637943833,"layerFullLocked":false,"layerHidden":false,"layerLocked":"false","maskRoundRectRadius":30,"border":"0","borderColor":"#00000000","borderDash":0,"borderDashGap":0,"borderStyle":0,"opacity":"1.0","rotateAngle":"90.0","backgroundColor":"#00000000","xPoint":"446.0","yPoint":"770.0","selected":"false","tiltX":0,"tiltY":0,"layoutParamsHeight":"-2","layoutParamsWidth":"-2","rootLayoutHeight":"202","rootLayoutWidth":"1108","textPadding":0,"viewType":"textView","zoomScale":"0.7200001","text":"رسول اکرم ﷺ نے فرمایا!","textAlignment":"textCenterAlignment","textVerticalAlignment":"textCenterVerticalAlignment","typeFaceName":"alqalam-telenor-regular","typeFaceType":"urdu","typeFaceLang":"urdu","textSize":"33.142857","textSizeSP":116,"textColor":"#FFFF0000","flipHorizontal":"1.0","flipVertical":"1.0","stroke":"3.0","strokeColor":"#FF000000","shadowRadius":"0.1","shadowThickness":"#00000001","shadowColor":"#FF170E0B","shadowX":"1.0","shadowY":"1.0","lineSpacing":"1.0","wordSpacing":0.0010000000474974513,"wordArc":0,"textBold":false,"textItalic":false,"textUnderline":false,"textEmboss":false,"textEmbossFull":false,"zeroSpans":[{"spanStart":4,"spanEnd":5},{"spanStart":14,"spanEnd":15}],"harfSpans":[{"xPoint":0,"yPoint":0,"textSize":115.5,"spanSizePerc":100,"spanStart":0,"spanEnd":1,"spanFormt":{}},{"xPoint":0,"yPoint":0,"textSize":115.5,"spanSizePerc":100,"spanStart":1,"spanEnd":3,"spanFormt":{}},{"xPoint":0,"yPoint":0,"textSize":115.5,"spanSizePerc":100,"spanStart":3,"spanEnd":4,"spanFormt":{}},{"xPoint":0,"yPoint":0,"textSize":115.5,"spanSizePerc":100,"spanStart":5,"spanEnd":6,"spanFormt":{}},{"xPoint":0,"yPoint":0,"textSize":115.5,"spanSizePerc":100,"spanStart":6,"spanEnd":8,"spanFormt":{}},{"xPoint":0,"yPoint":0,"textSize":115.5,"spanSizePerc":100,"spanStart":8,"spanEnd":10,"spanFormt":{}},{"xPoint":0,"yPoint":0,"textSize":115.5,"spanSizePerc":100,"spanStart":10,"spanEnd":11,"typeFaceName":"XP_Ziba","typeFaceType":"urdu","typeFaceLang":"urdu","spanFormt":{}},{"xPoint":0,"yPoint":0,"textSize":115.5,"spanSizePerc":100,"spanStart":11,"spanEnd":12,"spanFormt":{}},{"xPoint":0,"yPoint":0,"textSize":115.5,"spanSizePerc":100,"spanStart":12,"spanEnd":14,"spanFormt":{}},{"xPoint":0,"yPoint":0,"textSize":115.5,"spanSizePerc":100,"spanStart":15,"spanEnd":17,"spanFormt":{}},{"xPoint":0,"yPoint":0,"textSize":115.5,"spanSizePerc":100,"spanStart":17,"spanEnd":19,"spanFormt":{}},{"xPoint":0,"yPoint":0,"textSize":115.5,"spanSizePerc":100,"spanStart":19,"spanEnd":21,"spanFormt":{}},{"xPoint":0,"yPoint":0,"textSize":115.5,"spanSizePerc":100,"spanStart":21,"spanEnd":22,"spanFormt":{}},{"xPoint":0,"yPoint":0,"textSize":115.5,"spanSizePerc":100,"spanStart":22,"spanEnd":22,"spanFormt":{}}],"textDirection":4,"gradient":{"angle":90,"colors":["#FF0DB3CD","#FF0DB3CD","#FF7023E6","#FF7023E6"],"type":0,"grWidth":0,"grHeight":0},"textTextureScale":0,"projectName":"project_1632947218126"},{"viewId":1632637988149,"layerFullLocked":false,"layerHidden":false,"layerLocked":"false","maskRoundRectRadius":30,"border":"0","borderColor":"#00000000","borderDash":0,"borderDashGap":0,"borderStyle":0,"opacity":"1.0","rotateAngle":"90.0","backgroundColor":"#00000000","xPoint":"470.0","yPoint":"277.77774","selected":"false","tiltX":0,"tiltY":0,"layoutParamsHeight":"-2","layoutParamsWidth":"-2","rootLayoutHeight":"537","rootLayoutWidth":"1060","textPadding":0,"viewType":"textView","zoomScale":"0.7200001","text":"حسن اخـلاق","textAlignment":"textCenterAlignment","textVerticalAlignment":"textCenterVerticalAlignment","typeFaceName":"gandhara-suls-regular","typeFaceType":"urdu","typeFaceLang":"urdu","textSize":"59.42857","textSizeSP":208,"textColor":"#FF8E49A1","flipHorizontal":"1.0","flipVertical":"1.0","stroke":"0.0","strokeColor":"#FF696969","shadowRadius":"0.0","shadowThickness":"#00000001","shadowColor":"#FF444444","shadowX":"5.0","shadowY":"5.0","lineSpacing":"1.0","wordSpacing":0.0010000000474974513,"wordArc":0,"textBold":false,"textItalic":false,"textUnderline":false,"textEmboss":false,"textEmbossFull":false,"zeroSpans":[{"spanStart":3,"spanEnd":4}],"harfSpans":[{"xPoint":-44.75672912597656,"yPoint":1.7214202880859375,"textSize":206.5,"spanSizePerc":100,"spanStart":0,"spanEnd":3,"spanFormt":{}},{"xPoint":-29.8619384765625,"yPoint":37.05567932128906,"textSize":206.5,"spanSizePerc":100,"spanStart":4,"spanEnd":5,"spanFormt":{}},{"xPoint":171.0899200439453,"yPoint":-79.947265625,"textSize":206.5,"spanSizePerc":100,"spanStart":5,"spanEnd":9,"spanFormt":{}},{"xPoint":114.46965026855469,"yPoint":-69.84516906738281,"textSize":206.5,"spanSizePerc":100,"spanStart":9,"spanEnd":10,"spanFormt":{}}],"textDirection":4,"textTextureScale":0,"projectName":"project_1632947218126"}],"project_files":[],"project_description":"QDEIMAGITORIMAGITORIMAGITORاللہ کی رضا کے لیے دن بھر روزے رکھنا اور رات بھر نماز پڑھنا یقیناً یہ دونوں بہت بڑے اعمال ہیں اور انسان ان سے بہت بلند درجہ حاصل کرلیتا ہے۔ آپ ﷺ نے اخلاق عالیہ کی فضیلت بیان کرتے ہوۓ فرمایا کہ یہی درجہ انسان اچھے اخلاق سے بھی حاصل کر سکتا ہے۔﴿ترمذی شریف،2003﴾رسول اکرم ﷺ نے فرمایا!حسن اخـلاق"}