{"viewId":1666776979723,"height":2000,"width":2000,"bgOverlayGradient":{"angle":0,"colors":["#FF133E67","#FF3B8176"],"type":0,"grWidth":0,"grHeight":0},"backgroundOverlayColor":"#00000000","backgroundColor":"#FF398175","version":13,"subViews":[{"viewId":1646236937610,"layerFullLocked":false,"layerHidden":false,"layerLocked":"true","maskRoundRectRadius":0,"border":"2","borderColor":"#00000000","borderDash":0,"borderDashGap":0,"borderStyle":0,"opacity":"1.0","rotateAngle":"90.0","backgroundColor":"#00000000","xPoint":"0.0","yPoint":"0.0","selected":"false","tiltX":0,"tiltY":0,"layoutParamsHeight":"-1","layoutParamsWidth":"-1","rootLayoutHeight":"2000","rootLayoutWidth":"2000","textPadding":0,"viewType":"shapeView2","zoomScale":"0.7200001","shapeLayers":[{"shapeType":"shapePolygon","shapeVertices":[{"xPoint":462,"yPoint":1956.734375,"shapeBezChanged":false,"shapeVertBezPrev":{"xPoint":464.9617919921875,"yPoint":1904.9454345703125,"shapeBezChanged":true},"shapeVertBezNext":{"xPoint":762.7921142578125,"yPoint":1956.734375,"shapeBezChanged":false}},{"xPoint":1364.4666748046875,"yPoint":1956.734375,"shapeBezChanged":false,"shapeVertBezPrev":{"xPoint":1063.6744384765625,"yPoint":1956.734375,"shapeBezChanged":false},"shapeVertBezNext":{"xPoint":1457.6082763671875,"yPoint":1953.4078369140625,"shapeBezChanged":true}},{"xPoint":1532,"yPoint":1829.734375,"shapeBezChanged":false,"shapeVertBezPrev":{"xPoint":1529.286865234375,"yPoint":1890.086669921875,"shapeBezChanged":true},"shapeVertBezNext":{"xPoint":1249.3995361328125,"yPoint":1829.734375,"shapeBezChanged":false}},{"xPoint":684.113525390625,"yPoint":1829.734375,"shapeBezChanged":false,"shapeVertBezPrev":{"xPoint":966.714111328125,"yPoint":1829.734375,"shapeBezChanged":false},"shapeVertBezNext":{"xPoint":505.0008544921875,"yPoint":1828.61962890625,"shapeBezChanged":true}}],"shapeVerticesVer":1,"fillColor":"#FFFFFFFF","borderColor":"#FF061D61","border":0,"joinType":1,"rotateAngle":0,"cornerRadius":0,"borderDash":0,"borderDashGap":0,"borderStyle":0,"shadow":{"shadowRadius":0,"shadowColor":"#FF444444","shadowDist":0,"shadowAngle":45}}],"flipHorizontal":1,"flipVertical":1},{"viewId":1646236984474,"layerFullLocked":false,"layerHidden":false,"layerLocked":"true","maskRoundRectRadius":0,"border":"0","borderColor":"#00000000","borderDash":0,"borderDashGap":0,"borderStyle":0,"opacity":"1.0","rotateAngle":"90.0","backgroundColor":"#00000000","xPoint":"0.0","yPoint":"0.0","selected":"false","tiltX":0,"tiltY":0,"layoutParamsHeight":"-1","layoutParamsWidth":"-1","rootLayoutHeight":"2000","rootLayoutWidth":"2000","textPadding":0,"viewType":"shapeView2","zoomScale":"0.7200001","shapeLayers":[{"shapeType":"shapePolygon","shapeVertices":[{"xPoint":829.5364990234375,"yPoint":1956.734375,"shapeBezChanged":false,"shapeVertBezPrev":{"xPoint":832.62548828125,"yPoint":1904.9454345703125,"shapeBezChanged":true},"shapeVertBezNext":{"xPoint":1007.9432373046875,"yPoint":1956.7344970703125,"shapeBezChanged":false}},{"xPoint":1364.8094482421875,"yPoint":1956.734375,"shapeBezChanged":false,"shapeVertBezPrev":{"xPoint":1186.4034423828125,"yPoint":1956.7344970703125,"shapeBezChanged":false},"shapeVertBezNext":{"xPoint":1461.9512939453125,"yPoint":1953.4078369140625,"shapeBezChanged":true}},{"xPoint":1539.5364990234375,"yPoint":1829.734375,"shapeBezChanged":false,"shapeVertBezPrev":{"xPoint":1536.7073974609375,"yPoint":1890.086669921875,"shapeBezChanged":true},"shapeVertBezNext":{"xPoint":1380.1029052734375,"yPoint":1829.734375,"shapeBezChanged":false}},{"xPoint":1061.1881103515625,"yPoint":1829.734375,"shapeBezChanged":false,"shapeVertBezPrev":{"xPoint":1220.6217041015625,"yPoint":1829.734375,"shapeBezChanged":false},"shapeVertBezNext":{"xPoint":874.3836669921875,"yPoint":1828.61962890625,"shapeBezChanged":true}}],"shapeVerticesVer":1,"fillColor":"#FF018C72","borderColor":"#FF000000","border":0,"joinType":1,"rotateAngle":0,"cornerRadius":0,"borderDash":0,"borderDashGap":0,"borderStyle":0,"shadow":{"shadowRadius":0,"shadowColor":"#FF444444","shadowDist":0,"shadowAngle":45}}],"flipHorizontal":1,"flipVertical":1},{"viewId":1646237150883,"layerFullLocked":false,"layerHidden":false,"layerLocked":"true","maskRoundRectRadius":20,"border":"0","borderColor":"#00000000","borderDash":0,"borderDashGap":0,"borderStyle":0,"opacity":"1.0","rotateAngle":"90.0","backgroundColor":"#00000000","xPoint":"862.5597","yPoint":"1856.8278","selected":"false","tiltX":0,"tiltY":0,"layoutParamsHeight":"-2","layoutParamsWidth":"-2","rootLayoutHeight":"81","rootLayoutWidth":"587","textPadding":0,"viewType":"textView","zoomScale":"0.7200001","text":"IMAGITOR","textAlignment":"textCenterAlignment","textVerticalAlignment":"textTopAlignment","typeFaceName":"Prompt-Regular","typeFaceType":"all","typeFaceLang":"","textSize":"14.857142","textSizeSP":52,"textColor":"#FFFFFFFF","flipHorizontal":"1.0","flipVertical":"1.0","stroke":"0.0","strokeColor":"#FF696969","shadowRadius":"0.0","shadowThickness":1,"shadowColor":"#FF444444","shadowX":"5.0","shadowY":"5.0","lineSpacing":"1.0","wordSpacing":0.0010000000474974513,"wordArc":0,"textBold":false,"textItalic":false,"textUnderline":false,"textEmboss":false,"textEmbossFull":false,"zeroSpans":[],"harfSpans":[],"textDirection":1,"textTextureScale":0,"projectName":"project_1667845934483"},{"viewId":1664687383243,"layerFullLocked":false,"layerHidden":false,"layerLocked":"true","maskRoundRectRadius":20,"border":"0","borderColor":"#00000000","borderDash":0,"borderDashGap":0,"borderStyle":0,"opacity":"1.0","rotateAngle":"90.0","backgroundColor":"#00000000","xPoint":"510.43408","yPoint":"1827.7776","selected":"false","tiltX":0,"tiltY":0,"layoutParamsHeight":"-2","layoutParamsWidth":"-2","rootLayoutHeight":"142","rootLayoutWidth":"142","textPadding":25,"viewType":"shapeView","zoomScale":"0.7200001","text":"E","textAlignment":"textCenterAlignment","textVerticalAlignment":"textCenterVerticalAlignment","typeFaceName":"social_media.otf","typeFaceType":"icon","typeFaceLang":"","textSize":"2.2857144","textSizeSP":8,"textColor":"#FF018C72","flipHorizontal":"1.0","flipVertical":"1.0","stroke":"0.0","strokeColor":"#FF696969","shadowRadius":"0.0","shadowThickness":1,"shadowColor":"#FF444444","shadowX":"5.0","shadowY":"5.0","lineSpacing":"1.0","wordSpacing":0.0010000000474974513,"wordArc":0,"textBold":false,"textItalic":false,"textUnderline":false,"textEmboss":false,"textEmbossFull":false,"zeroSpans":[],"harfSpans":[],"textDirection":1,"textTextureScale":0,"projectName":"project_1667845934483","shapeViewVer":2},{"viewId":1646237025547,"layerFullLocked":false,"layerHidden":false,"layerLocked":"true","maskRoundRectRadius":20,"border":"0","borderColor":"#00000000","borderDash":0,"borderDashGap":0,"borderStyle":0,"opacity":"1.0","rotateAngle":"90.0","backgroundColor":"#00000000","xPoint":"608.29834","yPoint":"1827.9143","selected":"false","tiltX":0,"tiltY":0,"layoutParamsHeight":"-2","layoutParamsWidth":"-2","rootLayoutHeight":"142","rootLayoutWidth":"142","textPadding":25,"viewType":"shapeView","zoomScale":"0.7200001","text":"Q","textAlignment":"textCenterAlignment","textVerticalAlignment":"textCenterVerticalAlignment","typeFaceName":"social_media.otf","typeFaceType":"icon","typeFaceLang":"","textSize":"2.2857144","textSizeSP":8,"textColor":"#FF018C72","flipHorizontal":"1.0","flipVertical":"1.0","stroke":"0.0","strokeColor":"#FF696969","shadowRadius":"0.0","shadowThickness":1,"shadowColor":"#FF444444","shadowX":"5.0","shadowY":"5.0","lineSpacing":"1.0","wordSpacing":0.0010000000474974513,"wordArc":0,"textBold":false,"textItalic":false,"textUnderline":false,"textEmboss":false,"textEmbossFull":false,"zeroSpans":[],"harfSpans":[],"textDirection":1,"textTextureScale":0,"projectName":"project_1667845934483","shapeViewVer":2},{"viewId":1664687396714,"layerFullLocked":false,"layerHidden":false,"layerLocked":"true","maskRoundRectRadius":20,"border":"0","borderColor":"#00000000","borderDash":0,"borderDashGap":0,"borderStyle":0,"opacity":"1.0","rotateAngle":"90.0","backgroundColor":"#00000000","xPoint":"704.17065","yPoint":"1827.7776","selected":"false","tiltX":0,"tiltY":0,"layoutParamsHeight":"-2","layoutParamsWidth":"-2","rootLayoutHeight":"142","rootLayoutWidth":"142","textPadding":25,"viewType":"shapeView","zoomScale":"0.7200001","text":"M","textAlignment":"textCenterAlignment","textVerticalAlignment":"textCenterVerticalAlignment","typeFaceName":"social_media.otf","typeFaceType":"icon","typeFaceLang":"","textSize":"2.2857144","textSizeSP":8,"textColor":"#FF018C72","flipHorizontal":"1.0","flipVertical":"1.0","stroke":"0.0","strokeColor":"#FF696969","shadowRadius":"0.0","shadowThickness":1,"shadowColor":"#FF444444","shadowX":"5.0","shadowY":"5.0","lineSpacing":"1.0","wordSpacing":0.0010000000474974513,"wordArc":0,"textBold":false,"textItalic":false,"textUnderline":false,"textEmboss":false,"textEmbossFull":false,"zeroSpans":[],"harfSpans":[],"textDirection":1,"textTextureScale":0,"projectName":"project_1667845934483","shapeViewVer":2},{"viewId":1667098813292,"layerFullLocked":true,"layerHidden":false,"layerLocked":"false","maskRoundRectRadius":83,"border":"0","borderColor":"#00000000","borderDash":0,"borderDashGap":0,"borderStyle":0,"opacity":"1.0","rotateAngle":"90.0","backgroundColor":"#00000000","xPoint":"0.0","yPoint":"0.0","selected":"false","tiltX":0,"tiltY":0,"layoutParamsHeight":"-1","layoutParamsWidth":"-1","rootLayoutHeight":"2000","rootLayoutWidth":"2000","textPadding":0,"viewType":"shapeView2","zoomScale":"0.7200001","shapeLayers":[{"shapeType":"shapePolygon","shapeVertices":[{"xPoint":152.7777557373047,"yPoint":1721.588134765625,"shapeBezChanged":false,"shapeVertBezPrev":{"xPoint":152.7777557373047,"yPoint":1239.96923828125,"shapeBezChanged":false},"shapeVertBezNext":{"xPoint":713.3882446289062,"yPoint":1721.588134765625,"shapeBezChanged":false}},{"xPoint":1834.7777099609375,"yPoint":1721.588134765625,"shapeBezChanged":false,"shapeVertBezPrev":{"xPoint":1274.16796875,"yPoint":1721.588134765625,"shapeBezChanged":false},"shapeVertBezNext":{"xPoint":1834.7777099609375,"yPoint":1239.96923828125,"shapeBezChanged":false}},{"xPoint":1834.7777099609375,"yPoint":276.588134765625,"shapeBezChanged":false,"shapeVertBezPrev":{"xPoint":1834.7777099609375,"yPoint":758.2069091796875,"shapeBezChanged":false},"shapeVertBezNext":{"xPoint":1274.16796875,"yPoint":276.588134765625,"shapeBezChanged":false}},{"xPoint":152.7777557373047,"yPoint":276.588134765625,"shapeBezChanged":false,"shapeVertBezPrev":{"xPoint":713.3882446289062,"yPoint":276.588134765625,"shapeBezChanged":false},"shapeVertBezNext":{"xPoint":152.7777557373047,"yPoint":758.2069091796875,"shapeBezChanged":false}}],"shapeVerticesVer":1,"fillColor":"#FFF3FCFC","borderColor":"#FF000000","border":0,"joinType":1,"rotateAngle":0,"cornerRadius":83,"borderDash":0,"borderDashGap":0,"borderStyle":0,"shadow":{"shadowRadius":0,"shadowColor":"#FF444444","shadowDist":16,"shadowAngle":45}}],"flipHorizontal":1,"flipVertical":1},{"viewId":1667098834667,"layerFullLocked":true,"layerHidden":false,"layerLocked":"false","maskRoundRectRadius":83,"border":"0","borderColor":"#00000000","borderDash":0,"borderDashGap":0,"borderStyle":0,"opacity":"1.0","rotateAngle":"90.0","backgroundColor":"#00000000","xPoint":"0.0","yPoint":"0.0","selected":"false","tiltX":0,"tiltY":0,"layoutParamsHeight":"-1","layoutParamsWidth":"-1","rootLayoutHeight":"2000","rootLayoutWidth":"2000","textPadding":0,"viewType":"shapeView2","zoomScale":"0.7200001","shapeLayers":[{"shapeType":"shapePolygon","shapeVertices":[{"xPoint":236.58383178710938,"yPoint":1633.618408203125,"shapeBezChanged":false,"shapeVertBezPrev":{"xPoint":236.58383178710938,"yPoint":1216.660400390625,"shapeBezChanged":false},"shapeVertBezNext":{"xPoint":741.8665771484375,"yPoint":1633.618408203125,"shapeBezChanged":false}},{"xPoint":1752.5838623046875,"yPoint":1633.618408203125,"shapeBezChanged":false,"shapeVertBezPrev":{"xPoint":1247.3023681640625,"yPoint":1633.618408203125,"shapeBezChanged":false},"shapeVertBezNext":{"xPoint":1752.5838623046875,"yPoint":1216.660400390625,"shapeBezChanged":false}},{"xPoint":1752.5838623046875,"yPoint":382.61846923828125,"shapeBezChanged":false,"shapeVertBezPrev":{"xPoint":1752.5838623046875,"yPoint":799.5768432617188,"shapeBezChanged":false},"shapeVertBezNext":{"xPoint":1247.3023681640625,"yPoint":382.61846923828125,"shapeBezChanged":false}},{"xPoint":236.58383178710938,"yPoint":382.61846923828125,"shapeBezChanged":false,"shapeVertBezPrev":{"xPoint":741.8665771484375,"yPoint":382.61846923828125,"shapeBezChanged":false},"shapeVertBezNext":{"xPoint":236.58383178710938,"yPoint":799.5768432617188,"shapeBezChanged":false}}],"shapeVerticesVer":1,"fillColor":"#00000000","borderColor":"#FF018D73","border":6,"joinType":1,"rotateAngle":0,"cornerRadius":83,"borderDash":0,"borderDashGap":0,"borderStyle":0,"shadow":{"shadowRadius":0,"shadowColor":"#FF444444","shadowDist":16,"shadowAngle":45}}],"flipHorizontal":1,"flipVertical":1},{"viewId":1667099015221,"layerFullLocked":false,"layerHidden":false,"layerLocked":"false","maskRoundRectRadius":0,"border":"0","borderColor":"#00000000","borderDash":0,"borderDashGap":0,"borderStyle":0,"opacity":"1.0","rotateAngle":"90.0","backgroundColor":"#00000000","xPoint":"0.0","yPoint":"0.0","selected":"false","tiltX":0,"tiltY":0,"layoutParamsHeight":"-1","layoutParamsWidth":"-1","rootLayoutHeight":"2000","rootLayoutWidth":"2000","textPadding":0,"viewType":"shapeView2","zoomScale":"0.7200001","shapeLayers":[{"shapeType":"shapeSVG","shapeVertices":[{"xPoint":163.951904296875,"yPoint":1420.6961669921875,"shapeBezChanged":false,"shapeVertBezPrev":{"xPoint":163.951904296875,"yPoint":1420.6961669921875,"shapeBezChanged":true},"shapeVertBezNext":{"xPoint":165.54248046875,"yPoint":1424.9232177734375,"shapeBezChanged":true}},{"xPoint":192.7283172607422,"yPoint":1458.28125,"shapeBezChanged":false,"shapeVertBezPrev":{"xPoint":173.4729461669922,"yPoint":1443.763671875,"shapeBezChanged":true},"shapeVertBezNext":{"xPoint":211.98370361328125,"yPoint":1472.798828125,"shapeBezChanged":true}},{"xPoint":236.951904296875,"yPoint":1475.6961669921875,"shapeBezChanged":false,"shapeVertBezPrev":{"xPoint":232.767822265625,"yPoint":1475.3226318359375,"shapeBezChanged":true},"shapeVertBezNext":{"xPoint":235.4725341796875,"yPoint":1471.7332763671875,"shapeBezChanged":true}},{"xPoint":207.97299194335938,"yPoint":1438.1707763671875,"shapeBezChanged":false,"shapeVertBezPrev":{"xPoint":227.71023559570312,"yPoint":1453.053955078125,"shapeBezChanged":true},"shapeVertBezNext":{"xPoint":190.39535522460938,"yPoint":1424.91650390625,"shapeBezChanged":true}},{"xPoint":163.951904296875,"yPoint":1420.6961669921875,"shapeBezChanged":false,"shapeVertBezPrev":{"xPoint":168.61204528808594,"yPoint":1421.3323974609375,"shapeBezChanged":true},"shapeVertBezNext":{"xPoint":163.951904296875,"yPoint":1420.6961669921875,"shapeBezChanged":true}}],"shapeVerticesVer":1,"fillColor":"#FF018D73","borderColor":"#FF000000","border":0,"joinType":1,"rotateAngle":36,"cornerRadius":0,"borderDash":0,"borderDashGap":0,"borderStyle":0,"shadow":{"shadowRadius":0,"shadowColor":"#FF444444","shadowDist":16,"shadowAngle":45}}],"flipHorizontal":1,"flipVertical":1},{"viewId":1667099038537,"layerFullLocked":false,"layerHidden":false,"layerLocked":"false","maskRoundRectRadius":0,"border":"0","borderColor":"#00000000","borderDash":0,"borderDashGap":0,"borderStyle":0,"opacity":"1.0","rotateAngle":"90.0","backgroundColor":"#00000000","xPoint":"0.0","yPoint":"0.0","selected":"false","tiltX":0,"tiltY":0,"layoutParamsHeight":"-1","layoutParamsWidth":"-1","rootLayoutHeight":"2000","rootLayoutWidth":"2000","textPadding":0,"viewType":"shapeView2","zoomScale":"0.7200001","shapeLayers":[{"shapeType":"shapeSVG","shapeVertices":[{"xPoint":292.3489990234375,"yPoint":1437.4573974609375,"shapeBezChanged":false,"shapeVertBezPrev":{"xPoint":292.3489990234375,"yPoint":1437.4573974609375,"shapeBezChanged":true},"shapeVertBezNext":{"xPoint":291.085205078125,"yPoint":1440.761474609375,"shapeBezChanged":true}},{"xPoint":269.485595703125,"yPoint":1466.8421630859375,"shapeBezChanged":false,"shapeVertBezPrev":{"xPoint":284.784423828125,"yPoint":1455.491943359375,"shapeBezChanged":true},"shapeVertBezNext":{"xPoint":254.18670654296875,"yPoint":1478.1923828125,"shapeBezChanged":true}},{"xPoint":234.3489990234375,"yPoint":1480.4573974609375,"shapeBezChanged":false,"shapeVertBezPrev":{"xPoint":237.67333984375,"yPoint":1480.1656494140625,"shapeBezChanged":true},"shapeVertBezNext":{"xPoint":235.52447509765625,"yPoint":1477.3590087890625,"shapeBezChanged":true}},{"xPoint":257.37335205078125,"yPoint":1451.119140625,"shapeBezChanged":false,"shapeVertBezPrev":{"xPoint":241.69168090820312,"yPoint":1462.7548828125,"shapeBezChanged":true},"shapeVertBezNext":{"xPoint":271.339111328125,"yPoint":1440.756591796875,"shapeBezChanged":true}},{"xPoint":292.3489990234375,"yPoint":1437.4573974609375,"shapeBezChanged":false,"shapeVertBezPrev":{"xPoint":288.64654541015625,"yPoint":1437.9544677734375,"shapeBezChanged":true},"shapeVertBezNext":{"xPoint":292.3489990234375,"yPoint":1437.4573974609375,"shapeBezChanged":true}}],"shapeVerticesVer":1,"fillColor":"#FF018D73","borderColor":"#FF000000","border":0,"joinType":1,"rotateAngle":36,"cornerRadius":0,"borderDash":0,"borderDashGap":0,"borderStyle":0,"shadow":{"shadowRadius":0,"shadowColor":"#FF444444","shadowDist":16,"shadowAngle":45}}],"flipHorizontal":1,"flipVertical":1},{"viewId":1667099049185,"layerFullLocked":false,"layerHidden":false,"layerLocked":"false","maskRoundRectRadius":0,"border":"0","borderColor":"#00000000","borderDash":0,"borderDashGap":0,"borderStyle":0,"opacity":"1.0","rotateAngle":"90.0","backgroundColor":"#00000000","xPoint":"0.0","yPoint":"0.0","selected":"false","tiltX":0,"tiltY":0,"layoutParamsHeight":"-1","layoutParamsWidth":"-1","rootLayoutHeight":"2000","rootLayoutWidth":"2000","textPadding":0,"viewType":"shapeView2","zoomScale":"0.7200001","shapeLayers":[{"shapeType":"shapeSVG","shapeVertices":[{"xPoint":297.3489990234375,"yPoint":1338.007568359375,"shapeBezChanged":false,"shapeVertBezPrev":{"xPoint":297.3489990234375,"yPoint":1338.007568359375,"shapeBezChanged":true},"shapeVertBezNext":{"xPoint":296.16485595703125,"yPoint":1341.8992919921875,"shapeBezChanged":true}},{"xPoint":273.50543212890625,"yPoint":1373.5572509765625,"shapeBezChanged":false,"shapeVertBezPrev":{"xPoint":290.1224365234375,"yPoint":1359.304443359375,"shapeBezChanged":true},"shapeVertBezNext":{"xPoint":256.88824462890625,"yPoint":1387.810791015625,"shapeBezChanged":true}},{"xPoint":234.3489990234375,"yPoint":1392.007568359375,"shapeBezChanged":false,"shapeVertBezPrev":{"xPoint":238.13311767578125,"yPoint":1391.40478515625,"shapeBezChanged":true},"shapeVertBezNext":{"xPoint":235.44839477539062,"yPoint":1388.35888671875,"shapeBezChanged":true}},{"xPoint":258.38067626953125,"yPoint":1356.4984130859375,"shapeBezChanged":false,"shapeVertBezPrev":{"xPoint":241.347900390625,"yPoint":1371.109375,"shapeBezChanged":true},"shapeVertBezNext":{"xPoint":273.54962158203125,"yPoint":1343.4859619140625,"shapeBezChanged":true}},{"xPoint":297.3489990234375,"yPoint":1338.007568359375,"shapeBezChanged":false,"shapeVertBezPrev":{"xPoint":293.14825439453125,"yPoint":1338.8763427734375,"shapeBezChanged":true},"shapeVertBezNext":{"xPoint":297.3489990234375,"yPoint":1338.007568359375,"shapeBezChanged":true}}],"shapeVerticesVer":1,"fillColor":"#FF018D73","borderColor":"#FF000000","border":0,"joinType":1,"rotateAngle":30,"cornerRadius":0,"borderDash":0,"borderDashGap":0,"borderStyle":0,"shadow":{"shadowRadius":0,"shadowColor":"#FF444444","shadowDist":16,"shadowAngle":45}}],"flipHorizontal":1,"flipVertical":1},{"viewId":1667099062367,"layerFullLocked":false,"layerHidden":false,"layerLocked":"false","maskRoundRectRadius":0,"border":"0","borderColor":"#00000000","borderDash":0,"borderDashGap":0,"borderStyle":0,"opacity":"1.0","rotateAngle":"90.0","backgroundColor":"#00000000","xPoint":"0.0","yPoint":"0.0","selected":"false","tiltX":0,"tiltY":0,"layoutParamsHeight":"-1","layoutParamsWidth":"-1","rootLayoutHeight":"2000","rootLayoutWidth":"2000","textPadding":0,"viewType":"shapeView2","zoomScale":"0.7200001","shapeLayers":[{"shapeType":"shapeSVG","shapeVertices":[{"xPoint":1807.5626220703125,"yPoint":631.8018188476562,"shapeBezChanged":false,"shapeVertBezPrev":{"xPoint":1807.5626220703125,"yPoint":631.8018188476562,"shapeBezChanged":true},"shapeVertBezNext":{"xPoint":1806.56689453125,"yPoint":635.4404296875,"shapeBezChanged":true}},{"xPoint":1786.1083984375,"yPoint":665.4608764648438,"shapeBezChanged":false,"shapeVertBezPrev":{"xPoint":1801.4061279296875,"yPoint":651.7362060546875,"shapeBezChanged":true},"shapeVertBezNext":{"xPoint":1770.8101806640625,"yPoint":679.1856689453125,"shapeBezChanged":true}},{"xPoint":1749.5626220703125,"yPoint":683.8018188476562,"shapeBezChanged":false,"shapeVertBezPrev":{"xPoint":1753.1331787109375,"yPoint":683.1212768554688,"shapeBezChanged":true},"shapeVertBezNext":{"xPoint":1750.48583984375,"yPoint":680.3907470703125,"shapeBezChanged":true}},{"xPoint":1771.197021484375,"yPoint":650.173828125,"shapeBezChanged":false,"shapeVertBezPrev":{"xPoint":1755.5162353515625,"yPoint":664.2437744140625,"shapeBezChanged":true},"shapeVertBezNext":{"xPoint":1785.1614990234375,"yPoint":637.6436767578125,"shapeBezChanged":true}},{"xPoint":1807.5626220703125,"yPoint":631.8018188476562,"shapeBezChanged":false,"shapeVertBezPrev":{"xPoint":1803.605224609375,"yPoint":632.741943359375,"shapeBezChanged":true},"shapeVertBezNext":{"xPoint":1807.5626220703125,"yPoint":631.8018188476562,"shapeBezChanged":true}}],"shapeVerticesVer":1,"fillColor":"#FF018D73","borderColor":"#FF000000","border":0,"joinType":1,"rotateAngle":30,"cornerRadius":0,"borderDash":0,"borderDashGap":0,"borderStyle":0,"shadow":{"shadowRadius":0,"shadowColor":"#FF444444","shadowDist":16,"shadowAngle":45}}],"flipHorizontal":1,"flipVertical":1},{"viewId":1667099085269,"layerFullLocked":false,"layerHidden":false,"layerLocked":"false","maskRoundRectRadius":0,"border":"0","borderColor":"#00000000","borderDash":0,"borderDashGap":0,"borderStyle":0,"opacity":"1.0","rotateAngle":"90.0","backgroundColor":"#00000000","xPoint":"0.0","yPoint":"0.0","selected":"false","tiltX":0,"tiltY":0,"layoutParamsHeight":"-1","layoutParamsWidth":"-1","rootLayoutHeight":"2000","rootLayoutWidth":"2000","textPadding":0,"viewType":"shapeView2","zoomScale":"0.7200001","shapeLayers":[{"shapeType":"shapeSVG","shapeVertices":[{"xPoint":1809.7974853515625,"yPoint":710.0208129882812,"shapeBezChanged":false,"shapeVertBezPrev":{"xPoint":1809.7974853515625,"yPoint":710.0208129882812,"shapeBezChanged":true},"shapeVertBezNext":{"xPoint":1808.8017578125,"yPoint":713.659423828125,"shapeBezChanged":true}},{"xPoint":1788.34326171875,"yPoint":743.6798706054688,"shapeBezChanged":false,"shapeVertBezPrev":{"xPoint":1803.640869140625,"yPoint":729.9552001953125,"shapeBezChanged":true},"shapeVertBezNext":{"xPoint":1773.0450439453125,"yPoint":757.4046630859375,"shapeBezChanged":true}},{"xPoint":1751.7974853515625,"yPoint":762.0208129882812,"shapeBezChanged":false,"shapeVertBezPrev":{"xPoint":1755.3680419921875,"yPoint":761.3402709960938,"shapeBezChanged":true},"shapeVertBezNext":{"xPoint":1752.720703125,"yPoint":758.6097412109375,"shapeBezChanged":true}},{"xPoint":1773.431884765625,"yPoint":728.392822265625,"shapeBezChanged":false,"shapeVertBezPrev":{"xPoint":1757.7510986328125,"yPoint":742.4627685546875,"shapeBezChanged":true},"shapeVertBezNext":{"xPoint":1787.3963623046875,"yPoint":715.8626708984375,"shapeBezChanged":true}},{"xPoint":1809.7974853515625,"yPoint":710.0208129882812,"shapeBezChanged":false,"shapeVertBezPrev":{"xPoint":1805.8402099609375,"yPoint":710.9609375,"shapeBezChanged":true},"shapeVertBezNext":{"xPoint":1809.7974853515625,"yPoint":710.0208129882812,"shapeBezChanged":true}}],"shapeVerticesVer":1,"fillColor":"#FF018D73","borderColor":"#FF000000","border":0,"joinType":1,"rotateAngle":30,"cornerRadius":0,"borderDash":0,"borderDashGap":0,"borderStyle":0,"shadow":{"shadowRadius":0,"shadowColor":"#FF444444","shadowDist":16,"shadowAngle":45}}],"flipHorizontal":1,"flipVertical":1},{"viewId":1667099089220,"layerFullLocked":false,"layerHidden":false,"layerLocked":"false","maskRoundRectRadius":0,"border":"0","borderColor":"#00000000","borderDash":0,"borderDashGap":0,"borderStyle":0,"opacity":"1.0","rotateAngle":"90.0","backgroundColor":"#00000000","xPoint":"0.0","yPoint":"0.0","selected":"false","tiltX":0,"tiltY":0,"layoutParamsHeight":"-1","layoutParamsWidth":"-1","rootLayoutHeight":"2000","rootLayoutWidth":"2000","textPadding":0,"viewType":"shapeView2","zoomScale":"0.7200001","shapeLayers":[{"shapeType":"shapeSVG","shapeVertices":[{"xPoint":1688.1048583984375,"yPoint":628.4496459960938,"shapeBezChanged":false,"shapeVertBezPrev":{"xPoint":1688.1048583984375,"yPoint":628.4496459960938,"shapeBezChanged":true},"shapeVertBezNext":{"xPoint":1689.2205810546875,"yPoint":632.6478271484375,"shapeBezChanged":true}},{"xPoint":1712.148193359375,"yPoint":667.286865234375,"shapeBezChanged":false,"shapeVertBezPrev":{"xPoint":1695.0045166015625,"yPoint":651.450927734375,"shapeBezChanged":true},"shapeVertBezNext":{"xPoint":1729.2928466796875,"yPoint":683.1234741210938,"shapeBezChanged":true}},{"xPoint":1753.1048583984375,"yPoint":688.4496459960938,"shapeBezChanged":false,"shapeVertBezPrev":{"xPoint":1749.1031494140625,"yPoint":687.6646118164062,"shapeBezChanged":true},"shapeVertBezNext":{"xPoint":1752.0701904296875,"yPoint":684.513671875,"shapeBezChanged":true}},{"xPoint":1728.8597412109375,"yPoint":649.6482543945312,"shapeBezChanged":false,"shapeVertBezPrev":{"xPoint":1746.4326171875,"yPoint":665.8827514648438,"shapeBezChanged":true},"shapeVertBezNext":{"xPoint":1713.2093505859375,"yPoint":635.1904296875,"shapeBezChanged":true}},{"xPoint":1688.1048583984375,"yPoint":628.4496459960938,"shapeBezChanged":false,"shapeVertBezPrev":{"xPoint":1692.5399169921875,"yPoint":629.5343627929688,"shapeBezChanged":true},"shapeVertBezNext":{"xPoint":1688.1048583984375,"yPoint":628.4496459960938,"shapeBezChanged":true}}],"shapeVerticesVer":1,"fillColor":"#FF018D73","borderColor":"#FF000000","border":0,"joinType":1,"rotateAngle":30,"cornerRadius":0,"borderDash":0,"borderDashGap":0,"borderStyle":0,"shadow":{"shadowRadius":0,"shadowColor":"#FF444444","shadowDist":16,"shadowAngle":45}}],"flipHorizontal":1,"flipVertical":1},{"viewId":1667099098731,"layerFullLocked":false,"layerHidden":false,"layerLocked":"false","maskRoundRectRadius":0,"border":"0","borderColor":"#00000000","borderDash":0,"borderDashGap":0,"borderStyle":0,"opacity":"1.0","rotateAngle":"90.0","backgroundColor":"#00000000","xPoint":"0.0","yPoint":"0.0","selected":"false","tiltX":0,"tiltY":0,"layoutParamsHeight":"-1","layoutParamsWidth":"-1","rootLayoutHeight":"2000","rootLayoutWidth":"2000","textPadding":0,"viewType":"shapeView2","zoomScale":"0.7200001","shapeLayers":[{"shapeType":"shapeSVG","shapeVertices":[{"xPoint":1685.8699951171875,"yPoint":711.1382446289062,"shapeBezChanged":false,"shapeVertBezPrev":{"xPoint":1685.8699951171875,"yPoint":711.1382446289062,"shapeBezChanged":true},"shapeVertBezNext":{"xPoint":1686.9857177734375,"yPoint":715.33642578125,"shapeBezChanged":true}},{"xPoint":1709.913330078125,"yPoint":749.9754638671875,"shapeBezChanged":false,"shapeVertBezPrev":{"xPoint":1692.7696533203125,"yPoint":734.1395263671875,"shapeBezChanged":true},"shapeVertBezNext":{"xPoint":1727.0579833984375,"yPoint":765.8120727539062,"shapeBezChanged":true}},{"xPoint":1750.8699951171875,"yPoint":771.1382446289062,"shapeBezChanged":false,"shapeVertBezPrev":{"xPoint":1746.8682861328125,"yPoint":770.3532104492188,"shapeBezChanged":true},"shapeVertBezNext":{"xPoint":1749.8353271484375,"yPoint":767.2022705078125,"shapeBezChanged":true}},{"xPoint":1726.6248779296875,"yPoint":732.3368530273438,"shapeBezChanged":false,"shapeVertBezPrev":{"xPoint":1744.19775390625,"yPoint":748.5714111328125,"shapeBezChanged":true},"shapeVertBezNext":{"xPoint":1710.9744873046875,"yPoint":717.8790283203125,"shapeBezChanged":true}},{"xPoint":1685.8699951171875,"yPoint":711.1382446289062,"shapeBezChanged":false,"shapeVertBezPrev":{"xPoint":1690.3050537109375,"yPoint":712.2229614257812,"shapeBezChanged":true},"shapeVertBezNext":{"xPoint":1685.8699951171875,"yPoint":711.1382446289062,"shapeBezChanged":true}}],"shapeVerticesVer":1,"fillColor":"#FF018D73","borderColor":"#FF000000","border":0,"joinType":1,"rotateAngle":30,"cornerRadius":0,"borderDash":0,"borderDashGap":0,"borderStyle":0,"shadow":{"shadowRadius":0,"shadowColor":"#FF444444","shadowDist":16,"shadowAngle":45}}],"flipHorizontal":1,"flipVertical":1},{"viewId":1667098888004,"layerFullLocked":true,"layerHidden":false,"layerLocked":"false","maskRoundRectRadius":0,"border":"0","borderColor":"#00000000","borderDash":0,"borderDashGap":0,"borderStyle":0,"opacity":"1.0","rotateAngle":"90.0","backgroundColor":"#00000000","xPoint":"0.0","yPoint":"0.0","selected":"false","tiltX":0,"tiltY":0,"layoutParamsHeight":"-1","layoutParamsWidth":"-1","rootLayoutHeight":"2000","rootLayoutWidth":"2000","textPadding":0,"viewType":"shapeView2","zoomScale":"0.7200001","shapeLayers":[{"shapeType":"shapeSVG","shapeVertices":[{"xPoint":1835.801513671875,"yPoint":464.88885498046875,"shapeBezChanged":false,"shapeVertBezPrev":{"xPoint":1835.801513671875,"yPoint":464.88885498046875,"shapeBezChanged":true},"shapeVertBezNext":{"xPoint":1690.995361328125,"yPoint":464.88885498046875,"shapeBezChanged":true}},{"xPoint":1003.4818725585938,"yPoint":464.88885498046875,"shapeBezChanged":false,"shapeVertBezPrev":{"xPoint":1148.287353515625,"yPoint":464.88885498046875,"shapeBezChanged":true},"shapeVertBezNext":{"xPoint":888.2890014648438,"yPoint":464.88885498046875,"shapeBezChanged":true}},{"xPoint":885.8014526367188,"yPoint":352.25787353515625,"shapeBezChanged":false,"shapeVertBezPrev":{"xPoint":885.8014526367188,"yPoint":406.48779296875,"shapeBezChanged":true},"shapeVertBezNext":{"xPoint":885.8014526367188,"yPoint":300.7498779296875,"shapeBezChanged":true}},{"xPoint":885.8014526367188,"yPoint":213.8888702392578,"shapeBezChanged":false,"shapeVertBezPrev":{"xPoint":885.8541259765625,"yPoint":287.9241943359375,"shapeBezChanged":true},"shapeVertBezNext":{"xPoint":962.7262573242188,"yPoint":213.8888702392578,"shapeBezChanged":true}},{"xPoint":1718.98876953125,"yPoint":213.8888702392578,"shapeBezChanged":false,"shapeVertBezPrev":{"xPoint":1646.360107421875,"yPoint":213.8280487060547,"shapeBezChanged":true},"shapeVertBezNext":{"xPoint":1759.77734375,"yPoint":215.8869171142578,"shapeBezChanged":true}},{"xPoint":1835.801513671875,"yPoint":325.6953125,"shapeBezChanged":false,"shapeVertBezPrev":{"xPoint":1835.801513671875,"yPoint":223.98680114746094,"shapeBezChanged":true},"shapeVertBezNext":{"xPoint":1835.801513671875,"yPoint":473.87542724609375,"shapeBezChanged":true}},{"xPoint":1835.801513671875,"yPoint":464.88885498046875,"shapeBezChanged":false,"shapeVertBezPrev":{"xPoint":1835.801513671875,"yPoint":316.70880126953125,"shapeBezChanged":true},"shapeVertBezNext":{"xPoint":1835.801513671875,"yPoint":464.88885498046875,"shapeBezChanged":true}}],"shapeVerticesVer":1,"fillColor":"#FF018C72","borderColor":"#FF018C72","border":5,"joinType":1,"rotateAngle":0,"cornerRadius":0,"borderDash":0,"borderDashGap":0,"borderStyle":0,"shadow":{"shadowRadius":0,"shadowColor":"#FF444444","shadowDist":16,"shadowAngle":45}}],"flipHorizontal":1,"flipVertical":1},{"viewId":1667129861823,"layerFullLocked":true,"layerHidden":false,"layerLocked":"false","maskRoundRectRadius":83,"border":"0","borderColor":"#00000000","borderDash":0,"borderDashGap":0,"borderStyle":0,"opacity":"1.0","rotateAngle":"90.0","backgroundColor":"#00000000","xPoint":"152.77776","yPoint":"213.88887","selected":"false","tiltX":0,"tiltY":0,"layoutParamsHeight":"-2","layoutParamsWidth":"-2","rootLayoutHeight":"1507","rootLayoutWidth":"1683","textPadding":0,"viewType":"groupView","groupChildIds":[{"viewId":1667098813292,"groupChildProps":{"xPoint":152.7777557373047,"yPoint":276.588134765625,"width":1682,"height":1445,"border":0,"maskRoundRectRadius":83,"textPadding":0,"shadowRadius":0,"cornerRadius":83,"shadowDist":0}},{"viewId":1667098834667,"groupChildProps":{"xPoint":236.58383178710938,"yPoint":382.61846923828125,"width":1516,"height":1251,"border":6,"maskRoundRectRadius":83,"textPadding":0,"shadowRadius":0,"cornerRadius":83,"shadowDist":0}},{"viewId":1667099015221,"groupChildProps":{"xPoint":163.951904296875,"yPoint":1420.6961669921875,"width":73,"height":55,"border":0,"maskRoundRectRadius":0,"textPadding":0,"shadowRadius":0,"cornerRadius":0,"shadowDist":0}},{"viewId":1667099038537,"groupChildProps":{"xPoint":234.3489990234375,"yPoint":1437.4573974609375,"width":58,"height":43,"border":0,"maskRoundRectRadius":0,"textPadding":0,"shadowRadius":0,"cornerRadius":0,"shadowDist":0}},{"viewId":1667099049185,"groupChildProps":{"xPoint":234.3489990234375,"yPoint":1338.007568359375,"width":63,"height":54,"border":0,"maskRoundRectRadius":0,"textPadding":0,"shadowRadius":0,"cornerRadius":0,"shadowDist":0}},{"viewId":1667099062367,"groupChildProps":{"xPoint":1749.5626220703125,"yPoint":631.8018188476562,"width":58,"height":52,"border":0,"maskRoundRectRadius":0,"textPadding":0,"shadowRadius":0,"cornerRadius":0,"shadowDist":0}},{"viewId":1667099085269,"groupChildProps":{"xPoint":1751.7974853515625,"yPoint":710.0208129882812,"width":58,"height":52,"border":0,"maskRoundRectRadius":0,"textPadding":0,"shadowRadius":0,"cornerRadius":0,"shadowDist":0}},{"viewId":1667099089220,"groupChildProps":{"xPoint":1688.1048583984375,"yPoint":628.4496459960938,"width":65,"height":60,"border":0,"maskRoundRectRadius":0,"textPadding":0,"shadowRadius":0,"cornerRadius":0,"shadowDist":0}},{"viewId":1667099098731,"groupChildProps":{"xPoint":1685.8699951171875,"yPoint":711.1382446289062,"width":65,"height":60,"border":0,"maskRoundRectRadius":0,"textPadding":0,"shadowRadius":0,"cornerRadius":0,"shadowDist":0}},{"viewId":1667098888004,"groupChildProps":{"xPoint":885.8014526367188,"yPoint":213.8888702392578,"width":950,"height":250,"border":5,"maskRoundRectRadius":0,"textPadding":0,"shadowRadius":0,"cornerRadius":0,"shadowDist":0}},{"viewId":1667129861823,"groupChildProps":{"xPoint":152.7777557373047,"yPoint":213.8888702392578,"width":1683,"height":1507,"border":0,"maskRoundRectRadius":0,"textPadding":-1}}]},{"viewId":1667122163820,"layerFullLocked":false,"layerHidden":false,"layerLocked":"true","maskRoundRectRadius":33,"border":"0","borderColor":"#00000000","borderDash":0,"borderDashGap":0,"borderStyle":0,"opacity":"1.0","rotateAngle":"90.0","backgroundColor":"#00000000","xPoint":"891.7609","yPoint":"236.23708","selected":"false","tiltX":0,"tiltY":0,"layoutParamsHeight":"-2","layoutParamsWidth":"-2","rootLayoutHeight":"229","rootLayoutWidth":"955","textPadding":0,"viewType":"textView","zoomScale":"0.7200001","text":"ارشادِ نبوی ﷺ ہے !","textAlignment":"textCenterAlignment","textVerticalAlignment":"textTopAlignment","typeFaceName":"Sarem-Saamii-Regular","typeFaceType":"urdu","typeFaceLang":"urdu","textSize":"38.285713","textSizeSP":134,"textColor":"#FFFFFFFF","flipHorizontal":"1.0","flipVertical":"1.0","stroke":"0.0","strokeColor":"#FF696969","shadowRadius":"0.0","shadowThickness":1,"shadowColor":"#A8000000","shadowX":"5.0","shadowY":"5.0","lineSpacing":"1.0","wordSpacing":0.0010000000474974513,"wordArc":0,"textBold":false,"textItalic":false,"textUnderline":false,"textEmboss":false,"textEmbossFull":false,"zeroSpans":[],"harfSpans":[],"textDirection":1,"textTextureScale":0,"projectName":"project_1667845934483"},{"viewId":1651769143532,"layerFullLocked":false,"layerHidden":false,"layerLocked":"true","maskRoundRectRadius":34,"border":"0","borderColor":"#00000000","borderDash":0,"borderDashGap":0,"borderStyle":0,"opacity":"1.0","rotateAngle":"90.0","backgroundColor":"#FF018C72","xPoint":"316.91345","yPoint":"1480.116","selected":"false","tiltX":0,"tiltY":0,"layoutParamsHeight":"-2","layoutParamsWidth":"-2","rootLayoutHeight":"140","rootLayoutWidth":"676","textPadding":0,"viewType":"textView","zoomScale":"0.7200001","text":"(مشکوۃ  : 4816)","textAlignment":"textCenterAlignment","textVerticalAlignment":"textTopAlignment","typeFaceName":"alqalam-ferdaos-1-regular-1","typeFaceType":"urdu","typeFaceLang":"urdu","textSize":"20.0","textSizeSP":70,"textColor":"#FFFFFFFF","flipHorizontal":"1.0","flipVertical":"1.0","stroke":"0.0","strokeColor":"#FF696969","shadowRadius":"0.0","shadowThickness":1,"shadowColor":"#FF444444","shadowX":"5.0","shadowY":"5.0","lineSpacing":"1.0","wordSpacing":0.0010000000474974513,"wordArc":0,"textBold":false,"textItalic":false,"textUnderline":false,"textEmboss":false,"textEmbossFull":false,"zeroSpans":[],"harfSpans":[],"textDirection":1,"textTextureScale":0,"projectName":"project_1667845934483"},{"viewId":1651769039433,"layerFullLocked":false,"layerHidden":false,"layerLocked":"true","maskRoundRectRadius":31,"border":"0","borderColor":"#00000000","borderDash":0,"borderDashGap":0,"borderStyle":0,"opacity":"1.0","rotateAngle":"90.0","backgroundColor":"#00000000","xPoint":"313.88885","yPoint":"511.22217","selected":"false","tiltX":0,"tiltY":0,"layoutParamsHeight":"-2","layoutParamsWidth":"-2","rootLayoutHeight":"973","rootLayoutWidth":"1362","textPadding":8,"viewType":"textView","zoomScale":"0.7200001","text":"” اگر کوئی شخص کسی شخص کو فاسق یا کافر کہہ کر پکار تا ہے اور اگر وہ شخص (جسے پکارا جا رہا ہے) ایسے نہ ہو تو پھر وہ (بات) اس (کہنے والے) پر لوٹ آتی ہے ۔“","textAlignment":"textCenterAlignment","textVerticalAlignment":"textCenterVerticalAlignment","typeFaceName":"Mehr_Nastaliq_Web_2","typeFaceType":"urdu","typeFaceLang":"","textSize":"37.714287","textSizeSP":132,"textColor":"#FF111111","flipHorizontal":"1.0","flipVertical":"1.0","stroke":"0.0","strokeColor":"#FF696969","shadowRadius":"0.0","shadowThickness":1,"shadowColor":"#FF444444","shadowX":"5.0","shadowY":"5.0","lineSpacing":"1.0","wordSpacing":0.0010000000474974513,"wordArc":0,"textBold":false,"textItalic":false,"textUnderline":false,"textEmboss":false,"textEmbossFull":false,"zeroSpans":[],"harfSpans":[],"textDirection":4,"textTextureScale":0,"projectName":"project_1667845934483"}],"project_files":[],"project_description":"IMAGITOREQMارشادِ نبوی ﷺ ہے !(مشکوۃ  : 4816)” اگر کوئی شخص کسی شخص کو فاسق یا کافر کہہ کر پکار تا ہے اور اگر وہ شخص (جسے پکارا جا رہا ہے) ایسے نہ ہو تو پھر وہ (بات) اس (کہنے والے) پر لوٹ آتی ہے ۔“"}