{"viewId":1648217654514,"height":2000,"width":2000,"bgOverlayGradient":{"angle":90,"colors":["#FFF9D423","#FFE65C00"],"type":0,"grWidth":0,"grHeight":0},"backgroundOverlayColor":"#00000000","backgroundColor":"#FFFFFFFF","version":9,"subViews":[{"viewId":1648218458267,"layerFullLocked":true,"layerHidden":false,"layerLocked":"false","maskRoundRectRadius":0,"border":"0","borderColor":"#FF000000","borderDash":0,"borderDashGap":0,"borderStyle":0,"opacity":"0.3","rotateAngle":"90.0","backgroundColor":"#00000000","xPoint":"0.0","yPoint":"0.0","selected":"false","tiltX":0,"tiltY":0,"layoutParamsHeight":"-2","layoutParamsWidth":"-2","rootLayoutHeight":"2053","rootLayoutWidth":"2053","textPadding":0,"bitmapFilePath":".images\/1648218458267.imagitorImage","viewType":"imageView","zoomScale":"0.7200001","scaleType":"CENTER_CROP","compressionType":"PNG","flipHorizontal":1,"flipVertical":1,"tintColor":"#00000000","maskMode":0,"shadow":{"shadowRadius":0,"shadowColor":"#FF444444","shadowDist":15,"shadowAngle":45},"projectName":"project_1648323404966"},{"viewId":1648219421085,"layerFullLocked":true,"layerHidden":false,"layerLocked":"false","maskRoundRectRadius":0,"border":"0","borderColor":"#FF000000","borderDash":0,"borderDashGap":0,"borderStyle":0,"opacity":"1.0","rotateAngle":"90.0","backgroundColor":"#00000000","xPoint":"-91.66666","yPoint":"455.5555","selected":"false","tiltX":0,"tiltY":0,"layoutParamsHeight":"-2","layoutParamsWidth":"-2","rootLayoutHeight":"1506","rootLayoutWidth":"1360","textPadding":0,"bitmapFilePath":".images\/1648219421085.imagitorImage","viewType":"imageView","zoomScale":"0.7200001","scaleType":"FIT_CENTER","compressionType":"PNG","flipHorizontal":1,"flipVertical":1,"tintColor":"#00000000","maskMode":0,"shadow":{"shadowRadius":0,"shadowColor":"#FF444444","shadowDist":17.847768783569336,"shadowAngle":45},"projectName":"project_1648323404966"},{"viewId":1648218322488,"layerFullLocked":true,"layerHidden":false,"layerLocked":"false","maskRoundRectRadius":0,"border":"0","borderColor":"#00000000","borderDash":0,"borderDashGap":0,"borderStyle":0,"opacity":"1.0","rotateAngle":"90.0","backgroundColor":"#00000000","xPoint":"0.0","yPoint":"0.0","selected":"false","tiltX":0,"tiltY":0,"layoutParamsHeight":"-1","layoutParamsWidth":"-1","rootLayoutHeight":"2000","rootLayoutWidth":"2000","textPadding":0,"viewType":"shapeView2","zoomScale":"0.7200001","shapeLayers":[{"shapeType":"shapePolygon","shapeVertices":[{"xPoint":0,"yPoint":691.4144287109375,"shapeBezChanged":false,"shapeVertBezPrev":{"xPoint":0,"yPoint":460.96600341796875,"shapeBezChanged":false},"shapeVertBezNext":{"xPoint":104.20893859863281,"yPoint":296.6692199707031,"shapeBezChanged":true}},{"xPoint":605.7356567382812,"yPoint":85.78244018554688,"shapeBezChanged":false,"shapeVertBezPrev":{"xPoint":420.373291015625,"yPoint":460.0610046386719,"shapeBezChanged":true},"shapeVertBezNext":{"xPoint":777.2797241210938,"yPoint":461.2608337402344,"shapeBezChanged":true}},{"xPoint":1158.13623046875,"yPoint":691.1953125,"shapeBezChanged":false,"shapeVertBezPrev":{"xPoint":1114.2689208984375,"yPoint":342.8758544921875,"shapeBezChanged":true},"shapeVertBezNext":{"xPoint":1215.7890625,"yPoint":679.2122802734375,"shapeBezChanged":true}},{"xPoint":1354.2957763671875,"yPoint":721.80322265625,"shapeBezChanged":false,"shapeVertBezPrev":{"xPoint":1297.51318359375,"yPoint":686.7816162109375,"shapeBezChanged":true},"shapeVertBezNext":{"xPoint":1550.6251220703125,"yPoint":544.7781372070312,"shapeBezChanged":true}},{"xPoint":1870.5927734375,"yPoint":692.65869140625,"shapeBezChanged":false,"shapeVertBezPrev":{"xPoint":1726.2535400390625,"yPoint":589.5853271484375,"shapeBezChanged":true},"shapeVertBezNext":{"xPoint":1922.727783203125,"yPoint":650.259033203125,"shapeBezChanged":true}},{"xPoint":2000,"yPoint":616.3489990234375,"shapeBezChanged":false,"shapeVertBezPrev":{"xPoint":1962.593017578125,"yPoint":620.981201171875,"shapeBezChanged":true},"shapeVertBezNext":{"xPoint":2000,"yPoint":410.9198913574219,"shapeBezChanged":false}},{"xPoint":2000,"yPoint":0,"shapeBezChanged":false,"shapeVertBezPrev":{"xPoint":2000,"yPoint":205.4291229248047,"shapeBezChanged":false},"shapeVertBezNext":{"xPoint":1333.4000244140625,"yPoint":0,"shapeBezChanged":false}},{"xPoint":0,"yPoint":0,"shapeBezChanged":false,"shapeVertBezPrev":{"xPoint":666.6001586914062,"yPoint":0,"shapeBezChanged":false},"shapeVertBezNext":{"xPoint":0,"yPoint":230.44842529296875,"shapeBezChanged":false}}],"shapeVerticesVer":1,"fillColor":"#FFF9D417","borderColor":"#FF000000","border":0,"joinType":1,"rotateAngle":0,"cornerRadius":0,"borderDash":0,"borderDashGap":0,"borderStyle":0,"gradient":{"angle":0,"colors":["#FFF9D417","#FFE65200","#FFF9D423","#FFE65C00"],"type":0,"grWidth":0,"grHeight":0},"shadow":{"shadowRadius":0,"shadowColor":"#FF444444","shadowDist":15,"shadowAngle":45}}],"flipHorizontal":1,"flipVertical":1},{"viewId":1648217722006,"layerFullLocked":true,"layerHidden":false,"layerLocked":"false","maskRoundRectRadius":0,"border":"0","borderColor":"#00000000","borderDash":0,"borderDashGap":0,"borderStyle":0,"opacity":"1.0","rotateAngle":"90.0","backgroundColor":"#00000000","xPoint":"0.0","yPoint":"0.0","selected":"false","tiltX":0,"tiltY":0,"layoutParamsHeight":"-1","layoutParamsWidth":"-1","rootLayoutHeight":"2000","rootLayoutWidth":"2000","textPadding":0,"viewType":"shapeView2","zoomScale":"0.7200001","shapeLayers":[{"shapeType":"shapePolygon","shapeVertices":[{"xPoint":0,"yPoint":673.5100708007812,"shapeBezChanged":false,"shapeVertBezPrev":{"xPoint":0,"yPoint":449.0291748046875,"shapeBezChanged":false},"shapeVertBezNext":{"xPoint":104.20893859863281,"yPoint":278.7648620605469,"shapeBezChanged":true}},{"xPoint":605.7356567382812,"yPoint":49.03327941894531,"shapeBezChanged":false,"shapeVertBezPrev":{"xPoint":420.373291015625,"yPoint":423.31182861328125,"shapeBezChanged":true},"shapeVertBezNext":{"xPoint":777.2797241210938,"yPoint":424.51165771484375,"shapeBezChanged":true}},{"xPoint":1169.0303955078125,"yPoint":671.9178466796875,"shapeBezChanged":false,"shapeVertBezPrev":{"xPoint":1125.1630859375,"yPoint":323.598388671875,"shapeBezChanged":true},"shapeVertBezNext":{"xPoint":1226.6832275390625,"yPoint":659.934814453125,"shapeBezChanged":true}},{"xPoint":1354.0667724609375,"yPoint":705.0179443359375,"shapeBezChanged":false,"shapeVertBezPrev":{"xPoint":1297.2841796875,"yPoint":669.996337890625,"shapeBezChanged":true},"shapeVertBezNext":{"xPoint":1550.3961181640625,"yPoint":527.9928588867188,"shapeBezChanged":true}},{"xPoint":1870.5927734375,"yPoint":673.5580444335938,"shapeBezChanged":false,"shapeVertBezPrev":{"xPoint":1726.2535400390625,"yPoint":570.4846801757812,"shapeBezChanged":true},"shapeVertBezNext":{"xPoint":1922.727783203125,"yPoint":631.1583862304688,"shapeBezChanged":true}},{"xPoint":2000,"yPoint":593.6290893554688,"shapeBezChanged":false,"shapeVertBezPrev":{"xPoint":1962.593017578125,"yPoint":598.2612915039062,"shapeBezChanged":true},"shapeVertBezNext":{"xPoint":2000,"yPoint":395.77252197265625,"shapeBezChanged":false}},{"xPoint":2000,"yPoint":0,"shapeBezChanged":false,"shapeVertBezPrev":{"xPoint":2000,"yPoint":197.8565673828125,"shapeBezChanged":false},"shapeVertBezNext":{"xPoint":1333.4000244140625,"yPoint":0,"shapeBezChanged":false}},{"xPoint":0,"yPoint":0,"shapeBezChanged":false,"shapeVertBezPrev":{"xPoint":666.6001586914062,"yPoint":0,"shapeBezChanged":false},"shapeVertBezNext":{"xPoint":0,"yPoint":224.48089599609375,"shapeBezChanged":false}}],"shapeVerticesVer":1,"fillColor":"#FFE65C00","borderColor":"#FF000000","border":0,"joinType":1,"rotateAngle":0,"cornerRadius":0,"borderDash":0,"borderDashGap":0,"borderStyle":0,"gradient":{"angle":0,"colors":["#FFE65C00","#FFF9D423","#FFE65200","#FFF9D417"],"type":0,"grWidth":0,"grHeight":0},"shadow":{"shadowRadius":0,"shadowColor":"#FF444444","shadowDist":15,"shadowAngle":45}}],"flipHorizontal":1,"flipVertical":1},{"viewId":1648218149777,"layerFullLocked":true,"layerHidden":false,"layerLocked":"false","maskRoundRectRadius":0,"border":"0","borderColor":"#00000000","borderDash":0,"borderDashGap":0,"borderStyle":0,"opacity":"1.0","rotateAngle":"90.0","backgroundColor":"#00000000","xPoint":"0.0","yPoint":"0.0","selected":"false","tiltX":0,"tiltY":0,"layoutParamsHeight":"-1","layoutParamsWidth":"-1","rootLayoutHeight":"2000","rootLayoutWidth":"2000","textPadding":0,"viewType":"shapeView2","zoomScale":"0.7200001","shapeLayers":[{"shapeType":"shapePolygon","shapeVertices":[{"xPoint":0,"yPoint":653.8956909179688,"shapeBezChanged":false,"shapeVertBezPrev":{"xPoint":0,"yPoint":435.952392578125,"shapeBezChanged":false},"shapeVertBezNext":{"xPoint":104.20893859863281,"yPoint":259.57470703125,"shapeBezChanged":true}},{"xPoint":605.7357177734375,"yPoint":14.847223281860352,"shapeBezChanged":false,"shapeVertBezPrev":{"xPoint":420.373291015625,"yPoint":388.7235107421875,"shapeBezChanged":true},"shapeVertBezNext":{"xPoint":777.2797241210938,"yPoint":389.9220886230469,"shapeBezChanged":true}},{"xPoint":1182.9801025390625,"yPoint":649.6040649414062,"shapeBezChanged":false,"shapeVertBezPrev":{"xPoint":1139.11279296875,"yPoint":301.6589660644531,"shapeBezChanged":true},"shapeVertBezNext":{"xPoint":1240.6329345703125,"yPoint":637.6339721679688,"shapeBezChanged":true}},{"xPoint":1349.401123046875,"yPoint":675,"shapeBezChanged":false,"shapeVertBezPrev":{"xPoint":1292.6185302734375,"yPoint":640.0160522460938,"shapeBezChanged":true},"shapeVertBezNext":{"xPoint":1545.73046875,"yPoint":498.1651306152344,"shapeBezChanged":true}},{"xPoint":1868.85791015625,"yPoint":651.6616821289062,"shapeBezChanged":false,"shapeVertBezPrev":{"xPoint":1724.5186767578125,"yPoint":548.6991577148438,"shapeBezChanged":true},"shapeVertBezNext":{"xPoint":1920.992919921875,"yPoint":609.3076171875,"shapeBezChanged":true}},{"xPoint":2000,"yPoint":577.2640991210938,"shapeBezChanged":false,"shapeVertBezPrev":{"xPoint":1962.593017578125,"yPoint":581.8912963867188,"shapeBezChanged":true},"shapeVertBezNext":{"xPoint":2000,"yPoint":384.86199951171875,"shapeBezChanged":false}},{"xPoint":2000,"yPoint":0,"shapeBezChanged":false,"shapeVertBezPrev":{"xPoint":2000,"yPoint":192.40213012695312,"shapeBezChanged":false},"shapeVertBezNext":{"xPoint":1333.4000244140625,"yPoint":0,"shapeBezChanged":false}},{"xPoint":0,"yPoint":0,"shapeBezChanged":false,"shapeVertBezPrev":{"xPoint":666.6001586914062,"yPoint":0,"shapeBezChanged":false},"shapeVertBezNext":{"xPoint":0,"yPoint":217.94337463378906,"shapeBezChanged":false}}],"shapeVerticesVer":1,"fillColor":"#FFDACD9E","borderColor":"#FF000000","border":0,"joinType":1,"rotateAngle":0,"cornerRadius":0,"borderDash":0,"borderDashGap":0,"borderStyle":0,"shadow":{"shadowRadius":0,"shadowColor":"#FF444444","shadowDist":15,"shadowAngle":45}}],"flipHorizontal":1,"flipVertical":1},{"viewId":1648219771627,"layerFullLocked":true,"layerHidden":false,"layerLocked":"false","maskRoundRectRadius":0,"border":"0","borderColor":"#FF000000","borderDash":0,"borderDashGap":0,"borderStyle":0,"opacity":"0.3","rotateAngle":"90.0","backgroundColor":"#00000000","xPoint":"0.0","yPoint":"0.0","selected":"false","tiltX":0,"tiltY":0,"layoutParamsHeight":"-2","layoutParamsWidth":"-2","rootLayoutHeight":"675","rootLayoutWidth":"2053","textPadding":0,"bitmapFilePath":".images\/1648219771627.imagitorImage","viewType":"imageView","zoomScale":"0.7200001","scaleType":"CENTER_CROP","compressionType":"PNG","flipHorizontal":1,"flipVertical":1,"tintColor":"#00000000","maskMode":0,"shadow":{"shadowRadius":0,"shadowColor":"#FF444444","shadowDist":15,"shadowAngle":45},"projectName":"project_1648323404966"},{"viewId":1648219479568,"layerFullLocked":false,"layerHidden":false,"layerLocked":"false","maskRoundRectRadius":30,"border":"0","borderColor":"#00000000","borderDash":0,"borderDashGap":0,"borderStyle":0,"opacity":"1.0","rotateAngle":"90.0","backgroundColor":"#00000000","xPoint":"1199.9999","yPoint":"95.83332","selected":"false","tiltX":0,"tiltY":0,"layoutParamsHeight":"-2","layoutParamsWidth":"-2","rootLayoutHeight":"351","rootLayoutWidth":"706","textPadding":0,"viewType":"textView","zoomScale":"0.7200001","text":"آج کی حدیث","textAlignment":"textCenterAlignment","textVerticalAlignment":"textTopAlignment","typeFaceName":"diwani-letter-regular","typeFaceType":"urdu","typeFaceLang":"","textSize":"50.857143","textSizeSP":178,"textColor":"#FFFF0000","flipHorizontal":"1.0","flipVertical":"1.0","stroke":"5.0","strokeColor":"#FFFBF800","shadowRadius":"3.4","shadowThickness":1,"shadowColor":"#FF000000","shadowX":"3.0","shadowY":"7.0","lineSpacing":"1.0","wordSpacing":0.0010000000474974513,"wordArc":0,"textBold":false,"textItalic":false,"textUnderline":false,"textEmboss":false,"textEmbossFull":false,"zeroSpans":[],"harfSpans":[],"textDirection":1,"gradient":{"angle":90,"colors":["#400805","#400805","#B20000","#B20000"],"type":0,"grWidth":0,"grHeight":0},"textTextureScale":0,"projectName":"project_1648323404966"},{"viewId":1623552689309,"layerFullLocked":true,"layerHidden":false,"layerLocked":"false","maskRoundRectRadius":0,"border":"0","borderColor":"#00000000","borderDash":0,"borderDashGap":0,"borderStyle":0,"opacity":"1.0","rotateAngle":"90.0","backgroundColor":"#00000000","xPoint":"0.0","yPoint":"0.0","selected":"false","tiltX":0,"tiltY":0,"layoutParamsHeight":"-1","layoutParamsWidth":"-1","rootLayoutHeight":"2000","rootLayoutWidth":"2000","textPadding":0,"viewType":"shapeView2","zoomScale":"0.7200001","shapeLayers":[{"shapeType":"shapePolygon","shapeVertices":[{"xPoint":1475.9990234375,"yPoint":1934.369140625,"shapeBezChanged":false,"shapeVertBezPrev":{"xPoint":1475.9990234375,"yPoint":1539.075439453125,"shapeBezChanged":false},"shapeVertBezNext":{"xPoint":1566.6558837890625,"yPoint":1934.369140625,"shapeBezChanged":false}},{"xPoint":1747.9990234375,"yPoint":1934.369140625,"shapeBezChanged":false,"shapeVertBezPrev":{"xPoint":1657.3421630859375,"yPoint":1934.369140625,"shapeBezChanged":false},"shapeVertBezNext":{"xPoint":1747.9990234375,"yPoint":1539.075439453125,"shapeBezChanged":false}},{"xPoint":1747.9990234375,"yPoint":748.369140625,"shapeBezChanged":false,"shapeVertBezPrev":{"xPoint":1747.9990234375,"yPoint":1143.6627197265625,"shapeBezChanged":false},"shapeVertBezNext":{"xPoint":1657.3421630859375,"yPoint":748.369140625,"shapeBezChanged":false}},{"xPoint":1475.9990234375,"yPoint":748.369140625,"shapeBezChanged":false,"shapeVertBezPrev":{"xPoint":1566.6558837890625,"yPoint":748.369140625,"shapeBezChanged":false},"shapeVertBezNext":{"xPoint":1475.9990234375,"yPoint":1143.6627197265625,"shapeBezChanged":false}}],"shapeVerticesVer":1,"fillColor":"#FFFFEFBA","borderColor":"#FF000000","border":0,"joinType":1,"rotateAngle":0,"cornerRadius":0,"borderDash":0,"borderDashGap":0,"borderStyle":0,"gradient":{"angle":0,"colors":["#FFFFEFBA","#FFFFFFFF"],"type":0,"grWidth":0,"grHeight":0},"shadow":{"shadowRadius":0,"shadowColor":"#FF444444","shadowDist":14,"shadowAngle":45}}],"flipHorizontal":1,"flipVertical":1},{"viewId":1623552724607,"layerFullLocked":true,"layerHidden":false,"layerLocked":"false","maskRoundRectRadius":0,"border":"0","borderColor":"#00000000","borderDash":0,"borderDashGap":0,"borderStyle":0,"opacity":"1.0","rotateAngle":"90.0","backgroundColor":"#00000000","xPoint":"0.0","yPoint":"0.0","selected":"false","tiltX":0,"tiltY":0,"layoutParamsHeight":"-1","layoutParamsWidth":"-1","rootLayoutHeight":"2000","rootLayoutWidth":"2000","textPadding":0,"viewType":"shapeView2","zoomScale":"0.7200001","shapeLayers":[{"shapeType":"shapePolygon","shapeVertices":[{"xPoint":1458.93505859375,"yPoint":1459.954345703125,"shapeBezChanged":false,"shapeVertBezPrev":{"xPoint":1458.93505859375,"yPoint":1380.9620361328125,"shapeBezChanged":false},"shapeVertBezNext":{"xPoint":1560.257568359375,"yPoint":1459.954345703125,"shapeBezChanged":false}},{"xPoint":1762.93505859375,"yPoint":1459.954345703125,"shapeBezChanged":false,"shapeVertBezPrev":{"xPoint":1661.61279296875,"yPoint":1459.954345703125,"shapeBezChanged":false},"shapeVertBezNext":{"xPoint":1762.93505859375,"yPoint":1380.9620361328125,"shapeBezChanged":false}},{"xPoint":1762.93505859375,"yPoint":1222.954345703125,"shapeBezChanged":false,"shapeVertBezPrev":{"xPoint":1762.93505859375,"yPoint":1301.9464111328125,"shapeBezChanged":false},"shapeVertBezNext":{"xPoint":1661.61279296875,"yPoint":1222.954345703125,"shapeBezChanged":false}},{"xPoint":1458.93505859375,"yPoint":1222.954345703125,"shapeBezChanged":false,"shapeVertBezPrev":{"xPoint":1560.257568359375,"yPoint":1222.954345703125,"shapeBezChanged":false},"shapeVertBezNext":{"xPoint":1458.93505859375,"yPoint":1301.9464111328125,"shapeBezChanged":false}}],"shapeVerticesVer":1,"fillColor":"#FFE52D27","borderColor":"#00000000","border":4,"joinType":1,"rotateAngle":0,"cornerRadius":0,"borderDash":0,"borderDashGap":0,"borderStyle":0,"gradient":{"angle":0,"colors":["#FFE52D27","#FFB31217"],"type":0,"grWidth":0,"grHeight":0},"shadow":{"shadowRadius":0,"shadowColor":"#FF444444","shadowDist":14,"shadowAngle":45}}],"flipHorizontal":1,"flipVertical":1},{"viewId":1623556054822,"layerFullLocked":false,"layerHidden":false,"layerLocked":"true","maskRoundRectRadius":29,"border":"0","borderColor":"#00000000","borderDash":0,"borderDashGap":0,"borderStyle":0,"opacity":"1.0","rotateAngle":"90.0","backgroundColor":"#00000000","xPoint":"1484.0343","yPoint":"680.5555","selected":"false","tiltX":0,"tiltY":0,"layoutParamsHeight":"-2","layoutParamsWidth":"-2","rootLayoutHeight":"321","rootLayoutWidth":"254","textPadding":0,"viewType":"textView","zoomScale":"0.7200001","text":"27","textAlignment":"textCenterAlignment","textVerticalAlignment":"textTopAlignment","typeFaceName":"Oswald-Regular","typeFaceType":"all","typeFaceLang":"","textSize":"56.57143","textSizeSP":198,"textColor":"#FF3D9970","flipHorizontal":"1.0","flipVertical":"1.0","stroke":"0.0","strokeColor":"#FF696969","shadowRadius":"0.0","shadowThickness":1,"shadowColor":"#FF444444","shadowX":"5.0","shadowY":"5.0","lineSpacing":"1.0","wordSpacing":0.0010000000474974513,"wordArc":0,"textBold":false,"textItalic":false,"textUnderline":false,"textEmboss":false,"textEmbossFull":false,"zeroSpans":[],"harfSpans":[],"textDirection":1,"textTextureScale":0,"projectName":"project_1648323404966"},{"viewId":1623556135871,"layerFullLocked":true,"layerHidden":false,"layerLocked":"false","maskRoundRectRadius":29,"border":"0","borderColor":"#00000000","borderDash":0,"borderDashGap":0,"borderStyle":0,"opacity":"1.0","rotateAngle":"90.0","backgroundColor":"#00000000","xPoint":"1497.7952","yPoint":"848.4382","selected":"false","tiltX":0,"tiltY":0,"layoutParamsHeight":"-2","layoutParamsWidth":"-2","rootLayoutHeight":"150","rootLayoutWidth":"244","textPadding":0,"viewType":"textView","zoomScale":"0.7200001","text":"____","textAlignment":"textCenterAlignment","textVerticalAlignment":"textTopAlignment","typeFaceName":"Mehr Nastaliq Web","typeFaceType":"urdu","typeFaceLang":"","textSize":"24.0","textSizeSP":84,"textColor":"#FFFF0000","flipHorizontal":"1.0","flipVertical":"1.0","stroke":"0.0","strokeColor":"#FF696969","shadowRadius":"0.0","shadowThickness":1,"shadowColor":"#FF444444","shadowX":"5.0","shadowY":"5.0","lineSpacing":"1.0","wordSpacing":0.0010000000474974513,"wordArc":0,"textBold":false,"textItalic":false,"textUnderline":false,"textEmboss":false,"textEmbossFull":false,"zeroSpans":[],"harfSpans":[],"textDirection":1,"textTextureScale":0,"projectName":"project_1648323404966"},{"viewId":1623556174953,"layerFullLocked":true,"layerHidden":false,"layerLocked":"false","maskRoundRectRadius":29,"border":"0","borderColor":"#00000000","borderDash":0,"borderDashGap":0,"borderStyle":0,"opacity":"1.0","rotateAngle":"90.0","backgroundColor":"#00000000","xPoint":"1497.7952","yPoint":"986.0469","selected":"false","tiltX":0,"tiltY":0,"layoutParamsHeight":"-2","layoutParamsWidth":"-2","rootLayoutHeight":"150","rootLayoutWidth":"244","textPadding":0,"viewType":"textView","zoomScale":"0.7200001","text":"____","textAlignment":"textCenterAlignment","textVerticalAlignment":"textTopAlignment","typeFaceName":"Mehr Nastaliq Web","typeFaceType":"urdu","typeFaceLang":"","textSize":"24.0","textSizeSP":84,"textColor":"#FFFF0000","flipHorizontal":"1.0","flipVertical":"1.0","stroke":"0.0","strokeColor":"#FF696969","shadowRadius":"0.0","shadowThickness":1,"shadowColor":"#FF444444","shadowX":"5.0","shadowY":"5.0","lineSpacing":"1.0","wordSpacing":0.0010000000474974513,"wordArc":0,"textBold":false,"textItalic":false,"textUnderline":false,"textEmboss":false,"textEmbossFull":false,"zeroSpans":[],"harfSpans":[],"textDirection":1,"textTextureScale":0,"projectName":"project_1648323404966"},{"viewId":1623556219597,"layerFullLocked":false,"layerHidden":false,"layerLocked":"true","maskRoundRectRadius":29,"border":"0","borderColor":"#00000000","borderDash":0,"borderDashGap":0,"borderStyle":0,"opacity":"1.0","rotateAngle":"90.0","backgroundColor":"#00000000","xPoint":"1500.5474","yPoint":"886.9686","selected":"false","tiltX":0,"tiltY":0,"layoutParamsHeight":"-2","layoutParamsWidth":"-2","rootLayoutHeight":"247","rootLayoutWidth":"214","textPadding":0,"viewType":"textView","zoomScale":"0.7200001","text":"مارچ","textAlignment":"textCenterAlignment","textVerticalAlignment":"textTopAlignment","typeFaceName":"Mehr Nastaliq Web","typeFaceType":"urdu","typeFaceLang":"","textSize":"37.714287","textSizeSP":132,"textColor":"#FFFF0000","flipHorizontal":"1.0","flipVertical":"1.0","stroke":"0.0","strokeColor":"#FF696969","shadowRadius":"0.0","shadowThickness":1,"shadowColor":"#FF444444","shadowX":"5.0","shadowY":"5.0","lineSpacing":"1.0","wordSpacing":0.0010000000474974513,"wordArc":0,"textBold":false,"textItalic":false,"textUnderline":false,"textEmboss":false,"textEmbossFull":false,"zeroSpans":[],"harfSpans":[],"textDirection":1,"gradient":{"angle":90,"colors":["#e52d27","#b31217"],"type":0,"grWidth":0,"grHeight":0},"textTextureScale":0,"projectName":"project_1648323404966"},{"viewId":1623556262536,"layerFullLocked":false,"layerHidden":false,"layerLocked":"true","maskRoundRectRadius":29,"border":"0","borderColor":"#00000000","borderDash":0,"borderDashGap":0,"borderStyle":0,"opacity":"1.0","rotateAngle":"90.0","backgroundColor":"#00000000","xPoint":"1524.7665","yPoint":"1087.8773","selected":"false","tiltX":0,"tiltY":0,"layoutParamsHeight":"-2","layoutParamsWidth":"-2","rootLayoutHeight":"122","rootLayoutWidth":"181","textPadding":0,"viewType":"textView","zoomScale":"0.7200001","text":"2022","textAlignment":"textCenterAlignment","textVerticalAlignment":"textTopAlignment","typeFaceName":"Mehr Nastaliq Web","typeFaceType":"urdu","typeFaceLang":"","textSize":"20.571428","textSizeSP":72,"textColor":"#FF111111","flipHorizontal":"1.0","flipVertical":"1.0","stroke":"0.0","strokeColor":"#FF696969","shadowRadius":"0.0","shadowThickness":1,"shadowColor":"#FF444444","shadowX":"5.0","shadowY":"5.0","lineSpacing":"1.0","wordSpacing":0.0010000000474974513,"wordArc":0,"textBold":false,"textItalic":false,"textUnderline":false,"textEmboss":false,"textEmbossFull":false,"zeroSpans":[],"harfSpans":[],"textDirection":1,"textTextureScale":0,"projectName":"project_1648323404966"},{"viewId":1623556327463,"layerFullLocked":false,"layerHidden":false,"layerLocked":"true","maskRoundRectRadius":29,"border":"0","borderColor":"#00000000","borderDash":0,"borderDashGap":0,"borderStyle":0,"opacity":"1.0","rotateAngle":"90.0","backgroundColor":"#00000000","xPoint":"1484.0977","yPoint":"1650.2435","selected":"false","tiltX":0,"tiltY":0,"layoutParamsHeight":"-2","layoutParamsWidth":"-2","rootLayoutHeight":"321","rootLayoutWidth":"254","textPadding":0,"viewType":"textView","zoomScale":"0.7200001","text":"22","textAlignment":"textCenterAlignment","textVerticalAlignment":"textTopAlignment","typeFaceName":"Oswald-Regular","typeFaceType":"all","typeFaceLang":"","textSize":"56.57143","textSizeSP":198,"textColor":"#FF3D9970","flipHorizontal":"1.0","flipVertical":"1.0","stroke":"0.0","strokeColor":"#FF696969","shadowRadius":"0.0","shadowThickness":1,"shadowColor":"#FF444444","shadowX":"5.0","shadowY":"5.0","lineSpacing":"1.0","wordSpacing":0.0010000000474974513,"wordArc":0,"textBold":false,"textItalic":false,"textUnderline":false,"textEmboss":false,"textEmbossFull":false,"zeroSpans":[],"harfSpans":[],"textDirection":1,"textTextureScale":0,"projectName":"project_1648323404966"},{"viewId":1623556327469,"layerFullLocked":true,"layerHidden":false,"layerLocked":"false","maskRoundRectRadius":29,"border":"0","borderColor":"#00000000","borderDash":0,"borderDashGap":0,"borderStyle":0,"opacity":"1.0","rotateAngle":"90.0","backgroundColor":"#00000000","xPoint":"1492.2908","yPoint":"1448.5223","selected":"false","tiltX":0,"tiltY":0,"layoutParamsHeight":"-2","layoutParamsWidth":"-2","rootLayoutHeight":"150","rootLayoutWidth":"244","textPadding":0,"viewType":"textView","zoomScale":"0.7200001","text":"____","textAlignment":"textCenterAlignment","textVerticalAlignment":"textTopAlignment","typeFaceName":"Mehr Nastaliq Web","typeFaceType":"urdu","typeFaceLang":"","textSize":"22.857143","textSizeSP":80,"textColor":"#FFFF0000","flipHorizontal":"1.0","flipVertical":"1.0","stroke":"0.0","strokeColor":"#FF696969","shadowRadius":"0.0","shadowThickness":1,"shadowColor":"#FF444444","shadowX":"5.0","shadowY":"5.0","lineSpacing":"1.0","wordSpacing":0.0010000000474974513,"wordArc":0,"textBold":false,"textItalic":false,"textUnderline":false,"textEmboss":false,"textEmbossFull":false,"zeroSpans":[],"harfSpans":[],"textDirection":1,"textTextureScale":0,"projectName":"project_1648323404966"},{"viewId":1623556327476,"layerFullLocked":true,"layerHidden":false,"layerLocked":"false","maskRoundRectRadius":29,"border":"0","borderColor":"#00000000","borderDash":0,"borderDashGap":0,"borderStyle":0,"opacity":"1.0","rotateAngle":"90.0","backgroundColor":"#00000000","xPoint":"1488.9094","yPoint":"1600.5225","selected":"false","tiltX":0,"tiltY":0,"layoutParamsHeight":"-2","layoutParamsWidth":"-2","rootLayoutHeight":"150","rootLayoutWidth":"244","textPadding":0,"viewType":"textView","zoomScale":"0.7200001","text":"____","textAlignment":"textCenterAlignment","textVerticalAlignment":"textTopAlignment","typeFaceName":"Mehr Nastaliq Web","typeFaceType":"urdu","typeFaceLang":"","textSize":"24.0","textSizeSP":84,"textColor":"#FFFF0000","flipHorizontal":"1.0","flipVertical":"1.0","stroke":"0.0","strokeColor":"#FF696969","shadowRadius":"0.0","shadowThickness":1,"shadowColor":"#FF444444","shadowX":"5.0","shadowY":"5.0","lineSpacing":"1.0","wordSpacing":0.0010000000474974513,"wordArc":0,"textBold":false,"textItalic":false,"textUnderline":false,"textEmboss":false,"textEmbossFull":false,"zeroSpans":[],"harfSpans":[],"textDirection":1,"textTextureScale":0,"projectName":"project_1648323404966"},{"viewId":1623556327482,"layerFullLocked":false,"layerHidden":false,"layerLocked":"true","maskRoundRectRadius":29,"border":"0","borderColor":"#00000000","borderDash":0,"borderDashGap":0,"borderStyle":0,"opacity":"1.0","rotateAngle":"90.0","backgroundColor":"#00000000","xPoint":"1493.7211","yPoint":"1513.2686","selected":"false","tiltX":0,"tiltY":0,"layoutParamsHeight":"-2","layoutParamsWidth":"-2","rootLayoutHeight":"227","rootLayoutWidth":"233","textPadding":0,"viewType":"textView","zoomScale":"0.7200001","text":"شعبان","textAlignment":"textCenterAlignment","textVerticalAlignment":"textTopAlignment","typeFaceName":"Mehr Nastaliq Web","typeFaceType":"urdu","typeFaceLang":"","textSize":"37.142857","textSizeSP":130,"textColor":"#FFFF0000","flipHorizontal":"1.0","flipVertical":"1.0","stroke":"0.0","strokeColor":"#FF696969","shadowRadius":"0.0","shadowThickness":1,"shadowColor":"#FF444444","shadowX":"5.0","shadowY":"5.0","lineSpacing":"1.0","wordSpacing":0.0010000000474974513,"wordArc":0,"textBold":false,"textItalic":false,"textUnderline":false,"textEmboss":false,"textEmbossFull":false,"zeroSpans":[],"harfSpans":[],"textDirection":1,"gradient":{"angle":90,"colors":["#e52d27","#b31217"],"type":0,"grWidth":0,"grHeight":0},"textTextureScale":0,"projectName":"project_1648323404966"},{"viewId":1623556327489,"layerFullLocked":false,"layerHidden":false,"layerLocked":"true","maskRoundRectRadius":29,"border":"0","borderColor":"#00000000","borderDash":0,"borderDashGap":0,"borderStyle":0,"opacity":"1.0","rotateAngle":"90.0","backgroundColor":"#00000000","xPoint":"1525.7993","yPoint":"1456.1709","selected":"false","tiltX":0,"tiltY":0,"layoutParamsHeight":"-2","layoutParamsWidth":"-2","rootLayoutHeight":"122","rootLayoutWidth":"181","textPadding":0,"viewType":"textView","zoomScale":"0.7200001","text":"1443","textAlignment":"textCenterAlignment","textVerticalAlignment":"textTopAlignment","typeFaceName":"Mehr Nastaliq Web","typeFaceType":"urdu","typeFaceLang":"","textSize":"20.571428","textSizeSP":72,"textColor":"#FF111111","flipHorizontal":"1.0","flipVertical":"1.0","stroke":"0.0","strokeColor":"#FF696969","shadowRadius":"0.0","shadowThickness":1,"shadowColor":"#FF444444","shadowX":"5.0","shadowY":"5.0","lineSpacing":"1.0","wordSpacing":0.0010000000474974513,"wordArc":0,"textBold":false,"textItalic":false,"textUnderline":false,"textEmboss":false,"textEmbossFull":false,"zeroSpans":[],"harfSpans":[],"textDirection":1,"textTextureScale":0,"projectName":"project_1648323404966"},{"viewId":1623556510769,"layerFullLocked":false,"layerHidden":false,"layerLocked":"true","maskRoundRectRadius":29,"border":"0","borderColor":"#00000000","borderDash":0,"borderDashGap":0,"borderStyle":0,"opacity":"1.0","rotateAngle":"90.0","backgroundColor":"#00000000","xPoint":"1440.0","yPoint":"1153.9299","selected":"false","tiltX":0,"tiltY":0,"layoutParamsHeight":"-2","layoutParamsWidth":"-2","rootLayoutHeight":"359","rootLayoutWidth":"350","textPadding":0,"viewType":"textView","zoomScale":"0.7200001","text":"ہفتہ","textAlignment":"textCenterAlignment","textVerticalAlignment":"textTopAlignment","typeFaceName":"Mehr Nastaliq Web","typeFaceType":"urdu","typeFaceLang":"","textSize":"54.857143","textSizeSP":192,"textColor":"#FFFFFFFF","flipHorizontal":"1.0","flipVertical":"1.0","stroke":"0.0","strokeColor":"#FF696969","shadowRadius":"0.0","shadowThickness":1,"shadowColor":"#FF444444","shadowX":"5.0","shadowY":"5.0","lineSpacing":"1.0","wordSpacing":0.0010000000474974513,"wordArc":0,"textBold":false,"textItalic":false,"textUnderline":false,"textEmboss":false,"textEmbossFull":false,"zeroSpans":[],"harfSpans":[],"textDirection":1,"textTextureScale":0,"projectName":"project_1648323404966"},{"viewId":1648220216420,"layerFullLocked":false,"layerHidden":false,"layerLocked":"true","maskRoundRectRadius":30,"border":"0","borderColor":"#00000000","borderDash":0,"borderDashGap":0,"borderStyle":0,"opacity":"1.0","rotateAngle":"90.0","backgroundColor":"#00000000","xPoint":"216.0","yPoint":"624.0","selected":"false","tiltX":0,"tiltY":0,"layoutParamsHeight":"-2","layoutParamsWidth":"-2","rootLayoutHeight":"165","rootLayoutWidth":"754","textPadding":33,"viewType":"textView","zoomScale":"0.7200001","text":"رسول اکرم ﷺ نے فرمایا","textAlignment":"textCenterAlignment","textVerticalAlignment":"textTopAlignment","typeFaceName":"alqalam-juveria-kufi-regular-1","typeFaceType":"urdu","typeFaceLang":"","textSize":"25.714285","textSizeSP":90,"textColor":"#FF111111","flipHorizontal":"1.0","flipVertical":"1.0","stroke":"0.0","strokeColor":"#FF696969","shadowRadius":"0.0","shadowThickness":1,"shadowColor":"#FF444444","shadowX":"5.0","shadowY":"5.0","lineSpacing":"1.0","wordSpacing":0.0010000000474974513,"wordArc":0,"textBold":false,"textItalic":false,"textUnderline":false,"textEmboss":false,"textEmbossFull":false,"zeroSpans":[],"harfSpans":[],"textDirection":1,"textTextureScale":0,"projectName":"project_1648323404966"},{"viewId":1648220296758,"layerFullLocked":true,"layerHidden":false,"layerLocked":"false","maskRoundRectRadius":0,"border":"0","borderColor":"#00000000","borderDash":0,"borderDashGap":0,"borderStyle":0,"opacity":"1.0","rotateAngle":"90.0","backgroundColor":"#00000000","xPoint":"0.0","yPoint":"0.0","selected":"false","tiltX":0,"tiltY":0,"layoutParamsHeight":"-1","layoutParamsWidth":"-1","rootLayoutHeight":"2000","rootLayoutWidth":"2000","textPadding":0,"viewType":"shapeView2","zoomScale":"0.7200001","shapeLayers":[{"shapeType":"shapePen","shapeVertices":[{"xPoint":278,"yPoint":830.69873046875,"shapeBezChanged":false,"shapeVertBezNext":{"xPoint":471.8497619628906,"yPoint":830.4658203125,"shapeBezChanged":false}},{"xPoint":859.6075439453125,"yPoint":830,"shapeBezChanged":false,"shapeVertBezPrev":{"xPoint":665.7576904296875,"yPoint":830.23291015625,"shapeBezChanged":false}}],"shapeVerticesVer":1,"fillColor":"#00000000","borderColor":"#FFDF2925","border":4,"joinType":1,"rotateAngle":0,"cornerRadius":0,"borderDash":0,"borderDashGap":0,"borderStyle":0,"shadow":{"shadowRadius":0,"shadowColor":"#FF444444","shadowDist":15,"shadowAngle":45}}],"flipHorizontal":1,"flipVertical":1},{"viewId":1636260577478,"layerFullLocked":false,"layerHidden":false,"layerLocked":"true","maskRoundRectRadius":16,"border":"0","borderColor":"#00000000","borderDash":0,"borderDashGap":0,"borderStyle":0,"opacity":"1.0","rotateAngle":"90.0","backgroundColor":"#00000000","xPoint":"164.3826","yPoint":"914.0","selected":"false","tiltX":0,"tiltY":0,"layoutParamsHeight":"-2","layoutParamsWidth":"-2","rootLayoutHeight":"693","rootLayoutWidth":"865","textPadding":4,"viewType":"textView","zoomScale":"0.7200001","text":"مسلمانوں کو جو پریشانی غم ،رنج ، تکلیف اور دکھ پہنچتا ہے حتٰی کہ اگر اس کو کوئی کانٹا بھی چبھتا ہے تو اللہ تعالی اس تکلیف کو اس کے گناہوں کا کفارہ بنادیتا ہے۔","textAlignment":"textCenterAlignment","textVerticalAlignment":"textTopAlignment","typeFaceName":"urdu-emad-nastaleeq-regular","typeFaceType":"urdu","typeFaceLang":"","textSize":"25.0","textSizeSP":87,"textColor":"#FF111111","flipHorizontal":"1.0","flipVertical":"1.0","stroke":"0.0","strokeColor":"#FF696969","shadowRadius":"0.0","shadowThickness":1,"shadowColor":"#FF444444","shadowX":"5.0","shadowY":"5.0","lineSpacing":"0.8","wordSpacing":0.0010000000474974513,"wordArc":0,"textBold":false,"textItalic":false,"textUnderline":false,"textEmboss":false,"textEmbossFull":false,"zeroSpans":[],"harfSpans":[],"textDirection":1,"textTextureScale":0,"projectName":"project_1648323404966"},{"viewId":1623553743120,"layerFullLocked":false,"layerHidden":false,"layerLocked":"false","maskRoundRectRadius":19,"border":"0","borderColor":"#00000000","borderDash":0,"borderDashGap":0,"borderStyle":0,"opacity":"1.0","rotateAngle":"90.0","backgroundColor":"#00000000","xPoint":"315.11847","yPoint":"1681.46","selected":"false","tiltX":0,"tiltY":0,"layoutParamsHeight":"-2","layoutParamsWidth":"-2","rootLayoutHeight":"124","rootLayoutWidth":"515","textPadding":0,"viewType":"textView","zoomScale":"0.7200001","text":"صحیح بخاری (5641)","textAlignment":"textCenterAlignment","textVerticalAlignment":"textTopAlignment","typeFaceName":"Mehr Nastaliq Web","typeFaceType":"urdu","typeFaceLang":"","textSize":"19.0","textSizeSP":66,"textColor":"#FFDF2925","flipHorizontal":"1.0","flipVertical":"1.0","stroke":"0.0","strokeColor":"#FF696969","shadowRadius":"0.0","shadowThickness":1,"shadowColor":"#FF444444","shadowX":"5.0","shadowY":"5.0","lineSpacing":"0.8","wordSpacing":0.0010000000474974513,"wordArc":0,"textBold":false,"textItalic":false,"textUnderline":false,"textEmboss":false,"textEmbossFull":false,"zeroSpans":[],"harfSpans":[],"textDirection":1,"textTextureScale":0,"projectName":"project_1648323404966"},{"viewId":1647957415639,"layerFullLocked":true,"layerHidden":false,"layerLocked":"false","maskRoundRectRadius":0,"border":"0","borderColor":"#00000000","borderDash":0,"borderDashGap":0,"borderStyle":0,"opacity":"1.0","rotateAngle":"90.0","backgroundColor":"#00000000","xPoint":"0.0","yPoint":"0.0","selected":"false","tiltX":0,"tiltY":0,"layoutParamsHeight":"-1","layoutParamsWidth":"-1","rootLayoutHeight":"2000","rootLayoutWidth":"2000","textPadding":0,"viewType":"shapeView2","zoomScale":"0.7200001","shapeLayers":[{"shapeType":"shapePolygon","shapeVertices":[{"xPoint":400.5679016113281,"yPoint":1934.753662109375,"shapeBezChanged":false,"shapeVertBezPrev":{"xPoint":400.5679016113281,"yPoint":1907.4229736328125,"shapeBezChanged":false},"shapeVertBezNext":{"xPoint":569.2175903320312,"yPoint":1934.753662109375,"shapeBezChanged":false}},{"xPoint":906.5679321289062,"yPoint":1934.753662109375,"shapeBezChanged":false,"shapeVertBezPrev":{"xPoint":737.9180297851562,"yPoint":1934.753662109375,"shapeBezChanged":false},"shapeVertBezNext":{"xPoint":906.5679321289062,"yPoint":1907.4229736328125,"shapeBezChanged":false}},{"xPoint":906.5679321289062,"yPoint":1852.753662109375,"shapeBezChanged":false,"shapeVertBezPrev":{"xPoint":906.5679321289062,"yPoint":1880.08447265625,"shapeBezChanged":false},"shapeVertBezNext":{"xPoint":737.9180297851562,"yPoint":1852.753662109375,"shapeBezChanged":false}},{"xPoint":400.5679016113281,"yPoint":1852.753662109375,"shapeBezChanged":false,"shapeVertBezPrev":{"xPoint":569.2175903320312,"yPoint":1852.753662109375,"shapeBezChanged":false},"shapeVertBezNext":{"xPoint":400.5679016113281,"yPoint":1880.08447265625,"shapeBezChanged":false}}],"shapeVerticesVer":1,"fillColor":"#FFFFFFFF","borderColor":"#FF000000","border":5,"joinType":1,"rotateAngle":0,"cornerRadius":0,"borderDash":0,"borderDashGap":0,"borderStyle":0,"shadow":{"shadowRadius":0,"shadowColor":"#FF444444","shadowDist":5,"shadowAngle":45}}],"flipHorizontal":1,"flipVertical":1},{"viewId":1647957430582,"layerFullLocked":true,"layerHidden":false,"layerLocked":"false","maskRoundRectRadius":0,"border":"0","borderColor":"#00000000","borderDash":0,"borderDashGap":0,"borderStyle":0,"opacity":"1.0","rotateAngle":"90.0","backgroundColor":"#00000000","xPoint":"0.0","yPoint":"0.0","selected":"false","tiltX":0,"tiltY":0,"layoutParamsHeight":"-1","layoutParamsWidth":"-1","rootLayoutHeight":"2000","rootLayoutWidth":"2000","textPadding":0,"viewType":"shapeView2","zoomScale":"0.7200001","shapeLayers":[{"shapeType":"shapePolygon","shapeVertices":[{"xPoint":405.3568420410156,"yPoint":1934.753662109375,"shapeBezChanged":false,"shapeVertBezPrev":{"xPoint":405.3568420410156,"yPoint":1907.4229736328125,"shapeBezChanged":false},"shapeVertBezNext":{"xPoint":574.0065307617188,"yPoint":1934.753662109375,"shapeBezChanged":false}},{"xPoint":911.3568725585938,"yPoint":1934.753662109375,"shapeBezChanged":false,"shapeVertBezPrev":{"xPoint":742.7068481445312,"yPoint":1934.753662109375,"shapeBezChanged":false},"shapeVertBezNext":{"xPoint":911.3568725585938,"yPoint":1907.4229736328125,"shapeBezChanged":false}},{"xPoint":911.3568725585938,"yPoint":1852.753662109375,"shapeBezChanged":false,"shapeVertBezPrev":{"xPoint":911.3568725585938,"yPoint":1880.08447265625,"shapeBezChanged":false},"shapeVertBezNext":{"xPoint":742.7068481445312,"yPoint":1852.753662109375,"shapeBezChanged":false}},{"xPoint":405.3568420410156,"yPoint":1852.753662109375,"shapeBezChanged":false,"shapeVertBezPrev":{"xPoint":574.0065307617188,"yPoint":1852.753662109375,"shapeBezChanged":false},"shapeVertBezNext":{"xPoint":405.3568420410156,"yPoint":1880.08447265625,"shapeBezChanged":false}}],"shapeVerticesVer":1,"fillColor":"#FFFFFFFF","borderColor":"#FFFFFFFF","border":1,"joinType":1,"rotateAngle":0,"cornerRadius":0,"borderDash":0,"borderDashGap":0,"borderStyle":0,"shadow":{"shadowRadius":0,"shadowColor":"#FF444444","shadowDist":5,"shadowAngle":45}}],"flipHorizontal":1,"flipVertical":1},{"viewId":1646838523069,"layerFullLocked":false,"layerHidden":false,"layerLocked":"false","maskRoundRectRadius":8,"border":"0","borderColor":"#00000000","borderDash":0,"borderDashGap":0,"borderStyle":0,"opacity":"1.0","rotateAngle":"90.0","backgroundColor":"#00000000","xPoint":"618.0756","yPoint":"1864.2423","selected":"false","tiltX":0,"tiltY":0,"layoutParamsHeight":"-2","layoutParamsWidth":"-2","rootLayoutHeight":"60","rootLayoutWidth":"289","textPadding":0,"viewType":"textView","zoomScale":"0.7200001","text":"IMAGITOR","textAlignment":"textCenterAlignment","textVerticalAlignment":"textTopAlignment","typeFaceName":"Prompt-Regular","typeFaceType":"all","typeFaceLang":"","textSize":"11.428572","textSizeSP":40,"textColor":"#FF111111","flipHorizontal":"1.0","flipVertical":"1.0","stroke":"0.0","strokeColor":"#FF696969","shadowRadius":"0.0","shadowThickness":1,"shadowColor":"#FF444444","shadowX":"5.0","shadowY":"5.0","lineSpacing":"1.0","wordSpacing":0.0010000000474974513,"wordArc":0,"textBold":false,"textItalic":false,"textUnderline":false,"textEmboss":false,"textEmbossFull":false,"zeroSpans":[],"harfSpans":[],"textDirection":1,"textTextureScale":0,"projectName":"project_1648323404966"},{"viewId":1646838523061,"layerFullLocked":false,"layerHidden":false,"layerLocked":"true","maskRoundRectRadius":11,"border":"0","borderColor":"#00000000","borderDash":0,"borderDashGap":0,"borderStyle":0,"opacity":"1.0","rotateAngle":"90.0","backgroundColor":"#00000000","xPoint":"450.70853","yPoint":"1854.9172","selected":"false","tiltX":0,"tiltY":0,"layoutParamsHeight":"-2","layoutParamsWidth":"-2","rootLayoutHeight":"77","rootLayoutWidth":"77","textPadding":0,"viewType":"shapeView","zoomScale":"0.7200001","text":"Î","textAlignment":"textCenterAlignment","textVerticalAlignment":"textCenterVerticalAlignment","typeFaceName":"social_media.otf","typeFaceType":"icon","typeFaceLang":"","textSize":"1.1428572","textSizeSP":4,"textColor":"#FF0074D9","flipHorizontal":"1.0","flipVertical":"1.0","stroke":"0.0","strokeColor":"#FF696969","shadowRadius":"0.0","shadowThickness":1,"shadowColor":"#FF444444","shadowX":"5.0","shadowY":"5.0","lineSpacing":"1.0","wordSpacing":0.0010000000474974513,"wordArc":0,"textBold":false,"textItalic":false,"textUnderline":false,"textEmboss":false,"textEmbossFull":false,"zeroSpans":[],"harfSpans":[],"textDirection":1,"textTextureScale":0,"projectName":"project_1648323404966","shapeViewVer":2},{"viewId":1646930975467,"layerFullLocked":false,"layerHidden":false,"layerLocked":"true","maskRoundRectRadius":11,"border":"0","borderColor":"#00000000","borderDash":0,"borderDashGap":0,"borderStyle":0,"opacity":"1.0","rotateAngle":"90.0","backgroundColor":"#00000000","xPoint":"497.18057","yPoint":"1854.9172","selected":"false","tiltX":0,"tiltY":0,"layoutParamsHeight":"-2","layoutParamsWidth":"-2","rootLayoutHeight":"77","rootLayoutWidth":"77","textPadding":0,"viewType":"shapeView","zoomScale":"0.7200001","text":"Ö","textAlignment":"textCenterAlignment","textVerticalAlignment":"textCenterVerticalAlignment","typeFaceName":"social_media.otf","typeFaceType":"icon","typeFaceLang":"","textSize":"1.1428572","textSizeSP":4,"textColor":"#FFFF0000","flipHorizontal":"1.0","flipVertical":"1.0","stroke":"0.0","strokeColor":"#FF696969","shadowRadius":"0.0","shadowThickness":1,"shadowColor":"#FF444444","shadowX":"5.0","shadowY":"5.0","lineSpacing":"1.0","wordSpacing":0.0010000000474974513,"wordArc":0,"textBold":false,"textItalic":false,"textUnderline":false,"textEmboss":false,"textEmbossFull":false,"zeroSpans":[],"harfSpans":[],"textDirection":1,"gradient":{"angle":90,"colors":["#e52d27","#b31217"],"type":0,"grWidth":0,"grHeight":0},"textTextureScale":0,"projectName":"project_1648323404966","shapeViewVer":2},{"viewId":1646931009168,"layerFullLocked":false,"layerHidden":false,"layerLocked":"true","maskRoundRectRadius":11,"border":"0","borderColor":"#00000000","borderDash":0,"borderDashGap":0,"borderStyle":0,"opacity":"1.0","rotateAngle":"90.0","backgroundColor":"#00000000","xPoint":"549.5755","yPoint":"1854.9172","selected":"false","tiltX":0,"tiltY":0,"layoutParamsHeight":"-2","layoutParamsWidth":"-2","rootLayoutHeight":"77","rootLayoutWidth":"77","textPadding":0,"viewType":"shapeView","zoomScale":"0.7200001","text":"Í","textAlignment":"textCenterAlignment","textVerticalAlignment":"textCenterVerticalAlignment","typeFaceName":"social_media.otf","typeFaceType":"icon","typeFaceLang":"","textSize":"1.1428572","textSizeSP":4,"textColor":"#FF7FDBFF","flipHorizontal":"1.0","flipVertical":"1.0","stroke":"0.0","strokeColor":"#FF696969","shadowRadius":"0.0","shadowThickness":1,"shadowColor":"#FF444444","shadowX":"5.0","shadowY":"5.0","lineSpacing":"1.0","wordSpacing":0.0010000000474974513,"wordArc":0,"textBold":false,"textItalic":false,"textUnderline":false,"textEmboss":false,"textEmbossFull":false,"zeroSpans":[],"harfSpans":[],"textDirection":1,"textTextureScale":0,"projectName":"project_1648323404966","shapeViewVer":2},{"viewId":1627780742841,"layerFullLocked":true,"layerHidden":false,"layerLocked":"false","maskRoundRectRadius":0,"border":"0","borderColor":"#00000000","borderDash":0,"borderDashGap":0,"borderStyle":0,"opacity":"1.0","rotateAngle":"90.0","backgroundColor":"#00000000","xPoint":"0.0","yPoint":"0.0","selected":"false","tiltX":0,"tiltY":0,"layoutParamsHeight":"-1","layoutParamsWidth":"-1","rootLayoutHeight":"2000","rootLayoutWidth":"2000","textPadding":0,"viewType":"shapeView2","zoomScale":"0.7200001","shapeLayers":[{"shapeType":"shapePolygon","shapeVertices":[{"xPoint":354.1075439453125,"yPoint":1991.2220458984375,"shapeBezChanged":false,"shapeVertBezPrev":{"xPoint":344.8707275390625,"yPoint":1981.64697265625,"shapeBezChanged":false},"shapeVertBezNext":{"xPoint":363.69024658203125,"yPoint":1981.64697265625,"shapeBezChanged":false}},{"xPoint":382.8580627441406,"yPoint":1962.49365234375,"shapeBezChanged":false,"shapeVertBezPrev":{"xPoint":373.2752990722656,"yPoint":1972.0687255859375,"shapeBezChanged":false},"shapeVertBezNext":{"xPoint":396.4708557128906,"yPoint":1962.5155029296875,"shapeBezChanged":false}},{"xPoint":423.7004699707031,"yPoint":1962.5592041015625,"shapeBezChanged":false,"shapeVertBezPrev":{"xPoint":410.0875549316406,"yPoint":1962.53759765625,"shapeBezChanged":false},"shapeVertBezNext":{"xPoint":423.6821594238281,"yPoint":1949.440673828125,"shapeBezChanged":false}},{"xPoint":423.6459045410156,"yPoint":1923.1995849609375,"shapeBezChanged":false,"shapeVertBezPrev":{"xPoint":423.6639709472656,"yPoint":1936.3179931640625,"shapeBezChanged":false},"shapeVertBezNext":{"xPoint":432.5406799316406,"yPoint":1913.698974609375,"shapeBezChanged":false}},{"xPoint":450.3332824707031,"yPoint":1894.696044921875,"shapeBezChanged":false,"shapeVertBezPrev":{"xPoint":441.4381408691406,"yPoint":1904.1962890625,"shapeBezChanged":false},"shapeVertBezNext":{"xPoint":441.4311828613281,"yPoint":1884.883056640625,"shapeBezChanged":false}},{"xPoint":423.6242980957031,"yPoint":1865.2545166015625,"shapeBezChanged":false,"shapeVertBezPrev":{"xPoint":432.5262756347656,"yPoint":1875.0672607421875,"shapeBezChanged":false},"shapeVertBezNext":{"xPoint":423.6242980957031,"yPoint":1852.4312744140625,"shapeBezChanged":false}},{"xPoint":423.6242980957031,"yPoint":1826.7808837890625,"shapeBezChanged":false,"shapeVertBezPrev":{"xPoint":423.6242980957031,"yPoint":1839.6041259765625,"shapeBezChanged":false},"shapeVertBezNext":{"xPoint":410.0367736816406,"yPoint":1826.7808837890625,"shapeBezChanged":false}},{"xPoint":382.8580627441406,"yPoint":1826.7808837890625,"shapeBezChanged":false,"shapeVertBezPrev":{"xPoint":396.4454650878906,"yPoint":1826.7808837890625,"shapeBezChanged":false},"shapeVertBezNext":{"xPoint":373.2529602050781,"yPoint":1816.928955078125,"shapeBezChanged":false}},{"xPoint":354.04046630859375,"yPoint":1797.2220458984375,"shapeBezChanged":false,"shapeVertBezPrev":{"xPoint":363.64532470703125,"yPoint":1807.073974609375,"shapeBezChanged":false},"shapeVertBezNext":{"xPoint":344.82598876953125,"yPoint":1807.073974609375,"shapeBezChanged":false}},{"xPoint":326.3944091796875,"yPoint":1826.7808837890625,"shapeBezChanged":false,"shapeVertBezPrev":{"xPoint":335.6087646484375,"yPoint":1816.928955078125,"shapeBezChanged":false},"shapeVertBezNext":{"xPoint":312.8458251953125,"yPoint":1826.7808837890625,"shapeBezChanged":false}},{"xPoint":285.74517822265625,"yPoint":1826.7808837890625,"shapeBezChanged":false,"shapeVertBezPrev":{"xPoint":299.29345703125,"yPoint":1826.7808837890625,"shapeBezChanged":false},"shapeVertBezNext":{"xPoint":285.74517822265625,"yPoint":1840.073486328125,"shapeBezChanged":false}},{"xPoint":285.74517822265625,"yPoint":1866.6619873046875,"shapeBezChanged":false,"shapeVertBezPrev":{"xPoint":285.74517822265625,"yPoint":1853.3695068359375,"shapeBezChanged":false},"shapeVertBezNext":{"xPoint":276.6087646484375,"yPoint":1876.005859375,"shapeBezChanged":false}},{"xPoint":258.33331298828125,"yPoint":1894.6964111328125,"shapeBezChanged":false,"shapeVertBezPrev":{"xPoint":267.46966552734375,"yPoint":1885.3525390625,"shapeBezChanged":false},"shapeVertBezNext":{"xPoint":267.46966552734375,"yPoint":1903.6490478515625,"shapeBezChanged":false}},{"xPoint":285.74517822265625,"yPoint":1921.5570068359375,"shapeBezChanged":false,"shapeVertBezPrev":{"xPoint":276.6087646484375,"yPoint":1912.6044921875,"shapeBezChanged":false},"shapeVertBezNext":{"xPoint":285.74517822265625,"yPoint":1935.2012939453125,"shapeBezChanged":false}},{"xPoint":285.74517822265625,"yPoint":1962.49365234375,"shapeBezChanged":false,"shapeVertBezPrev":{"xPoint":285.74517822265625,"yPoint":1948.849609375,"shapeBezChanged":false},"shapeVertBezNext":{"xPoint":299.29345703125,"yPoint":1962.49365234375,"shapeBezChanged":false}},{"xPoint":326.3944091796875,"yPoint":1962.49365234375,"shapeBezChanged":false,"shapeVertBezPrev":{"xPoint":312.8458251953125,"yPoint":1962.49365234375,"shapeBezChanged":false},"shapeVertBezNext":{"xPoint":335.631103515625,"yPoint":1972.0687255859375,"shapeBezChanged":false}}],"shapeVerticesVer":1,"fillColor":"#FFFFFFFF","borderColor":"#FFB48F35","border":0,"joinType":1,"rotateAngle":0,"cornerRadius":0,"borderDash":0,"borderDashGap":0,"borderStyle":0,"shadow":{"shadowRadius":0,"shadowColor":"#FF444444","shadowDist":0,"shadowAngle":45}}],"flipHorizontal":1,"flipVertical":1},{"viewId":1647957554801,"layerFullLocked":true,"layerHidden":false,"layerLocked":"true","maskRoundRectRadius":0,"border":"0","borderColor":"#00000000","borderDash":0,"borderDashGap":0,"borderStyle":0,"opacity":"1.0","rotateAngle":"90.0","backgroundColor":"#00000000","xPoint":"0.0","yPoint":"0.0","selected":"false","tiltX":0,"tiltY":0,"layoutParamsHeight":"-1","layoutParamsWidth":"-1","rootLayoutHeight":"2000","rootLayoutWidth":"2000","textPadding":0,"viewType":"shapeView2","zoomScale":"0.7200001","shapeLayers":[{"shapeType":"shapePolygon","shapeVertices":[{"xPoint":354.28070068359375,"yPoint":1980.5960693359375,"shapeBezChanged":false,"shapeVertBezPrev":{"xPoint":345.86175537109375,"yPoint":1971.9586181640625,"shapeBezChanged":false},"shapeVertBezNext":{"xPoint":363.01495361328125,"yPoint":1971.9586181640625,"shapeBezChanged":false}},{"xPoint":380.4857482910156,"yPoint":1954.6815185546875,"shapeBezChanged":false,"shapeVertBezPrev":{"xPoint":371.7513732910156,"yPoint":1963.3187255859375,"shapeBezChanged":false},"shapeVertBezNext":{"xPoint":392.8930969238281,"yPoint":1954.701171875,"shapeBezChanged":false}},{"xPoint":417.7117004394531,"yPoint":1954.7403564453125,"shapeBezChanged":false,"shapeVertBezPrev":{"xPoint":405.3043518066406,"yPoint":1954.720703125,"shapeBezChanged":false},"shapeVertBezNext":{"xPoint":417.6953430175781,"yPoint":1942.90673828125,"shapeBezChanged":false}},{"xPoint":417.6618957519531,"yPoint":1919.235595703125,"shapeBezChanged":false,"shapeVertBezPrev":{"xPoint":417.6784973144531,"yPoint":1931.0693359375,"shapeBezChanged":false},"shapeVertBezNext":{"xPoint":425.7690734863281,"yPoint":1910.66552734375,"shapeBezChanged":false}},{"xPoint":441.9864807128906,"yPoint":1893.523681640625,"shapeBezChanged":false,"shapeVertBezPrev":{"xPoint":433.8789367675781,"yPoint":1902.0933837890625,"shapeBezChanged":false},"shapeVertBezNext":{"xPoint":433.8724670410156,"yPoint":1884.671630859375,"shapeBezChanged":false}},{"xPoint":417.6422424316406,"yPoint":1866.965576171875,"shapeBezChanged":false,"shapeVertBezPrev":{"xPoint":425.7561340332031,"yPoint":1875.8173828125,"shapeBezChanged":false},"shapeVertBezNext":{"xPoint":417.6422424316406,"yPoint":1855.398193359375,"shapeBezChanged":false}},{"xPoint":417.6422424316406,"yPoint":1832.259765625,"shapeBezChanged":false,"shapeVertBezPrev":{"xPoint":417.6422424316406,"yPoint":1843.827392578125,"shapeBezChanged":false},"shapeVertBezNext":{"xPoint":405.2579650878906,"yPoint":1832.259765625,"shapeBezChanged":false}},{"xPoint":380.4857482910156,"yPoint":1832.259765625,"shapeBezChanged":false,"shapeVertBezPrev":{"xPoint":392.8700256347656,"yPoint":1832.259765625,"shapeBezChanged":false},"shapeVertBezNext":{"xPoint":371.7309875488281,"yPoint":1823.373046875,"shapeBezChanged":false}},{"xPoint":354.21954345703125,"yPoint":1805.5960693359375,"shapeBezChanged":false,"shapeVertBezPrev":{"xPoint":362.97406005859375,"yPoint":1814.483154296875,"shapeBezChanged":false},"shapeVertBezNext":{"xPoint":345.82098388671875,"yPoint":1814.483154296875,"shapeBezChanged":false}},{"xPoint":329.02130126953125,"yPoint":1832.259765625,"shapeBezChanged":false,"shapeVertBezPrev":{"xPoint":337.41986083984375,"yPoint":1823.373046875,"shapeBezChanged":false},"shapeVertBezNext":{"xPoint":316.67242431640625,"yPoint":1832.259765625,"shapeBezChanged":false}},{"xPoint":291.9713134765625,"yPoint":1832.259765625,"shapeBezChanged":false,"shapeVertBezPrev":{"xPoint":304.31988525390625,"yPoint":1832.259765625,"shapeBezChanged":false},"shapeVertBezNext":{"xPoint":291.9713134765625,"yPoint":1844.2506103515625,"shapeBezChanged":false}},{"xPoint":291.9713134765625,"yPoint":1868.235107421875,"shapeBezChanged":false,"shapeVertBezPrev":{"xPoint":291.9713134765625,"yPoint":1856.24462890625,"shapeBezChanged":false},"shapeVertBezNext":{"xPoint":283.64385986328125,"yPoint":1876.6639404296875,"shapeBezChanged":false}},{"xPoint":266.98651123046875,"yPoint":1893.5240478515625,"shapeBezChanged":false,"shapeVertBezPrev":{"xPoint":275.31402587890625,"yPoint":1885.09521484375,"shapeBezChanged":false},"shapeVertBezNext":{"xPoint":275.31402587890625,"yPoint":1901.5999755859375,"shapeBezChanged":false}},{"xPoint":291.9713134765625,"yPoint":1917.7540283203125,"shapeBezChanged":false,"shapeVertBezPrev":{"xPoint":283.64385986328125,"yPoint":1909.6781005859375,"shapeBezChanged":false},"shapeVertBezNext":{"xPoint":291.9713134765625,"yPoint":1930.061767578125,"shapeBezChanged":false}},{"xPoint":291.9713134765625,"yPoint":1954.6815185546875,"shapeBezChanged":false,"shapeVertBezPrev":{"xPoint":291.9713134765625,"yPoint":1942.373291015625,"shapeBezChanged":false},"shapeVertBezNext":{"xPoint":304.31988525390625,"yPoint":1954.6815185546875,"shapeBezChanged":false}},{"xPoint":329.02130126953125,"yPoint":1954.6815185546875,"shapeBezChanged":false,"shapeVertBezPrev":{"xPoint":316.67242431640625,"yPoint":1954.6815185546875,"shapeBezChanged":false},"shapeVertBezNext":{"xPoint":337.44024658203125,"yPoint":1963.3187255859375,"shapeBezChanged":false}}],"shapeVerticesVer":1,"fillColor":"#FFE65C00","borderColor":"#FFB48F35","border":0,"joinType":1,"rotateAngle":0,"cornerRadius":0,"borderDash":0,"borderDashGap":0,"borderStyle":0,"gradient":{"angle":90,"colors":["#FFE65C00","#FFF9D423"],"type":0,"grWidth":0,"grHeight":0},"shadow":{"shadowRadius":0,"shadowColor":"#FF444444","shadowDist":0,"shadowAngle":45}}],"flipHorizontal":1,"flipVertical":1},{"viewId":1615547862965,"layerFullLocked":false,"layerHidden":false,"layerLocked":"true","maskRoundRectRadius":16,"border":"2","borderColor":"#00000000","borderDash":0,"borderDashGap":0,"borderStyle":0,"opacity":"1.0","rotateAngle":"90.0","backgroundColor":"#00000000","xPoint":"0.0","yPoint":"0.0","selected":"false","tiltX":0,"tiltY":0,"layoutParamsHeight":"-1","layoutParamsWidth":"-1","rootLayoutHeight":"2000","rootLayoutWidth":"2000","textPadding":0,"viewType":"shapeView2","zoomScale":"0.7200001","shapeLayers":[{"shapeType":"shapePolygon","shapeVertices":[{"xPoint":318.25848388671875,"yPoint":1931.119873046875,"shapeBezChanged":false,"shapeVertBezPrev":{"xPoint":318.25848388671875,"yPoint":1906.122314453125,"shapeBezChanged":false},"shapeVertBezNext":{"xPoint":342.58953857421875,"yPoint":1931.119873046875,"shapeBezChanged":false}},{"xPoint":391.2584533691406,"yPoint":1931.119873046875,"shapeBezChanged":false,"shapeVertBezPrev":{"xPoint":366.92767333984375,"yPoint":1931.119873046875,"shapeBezChanged":false},"shapeVertBezNext":{"xPoint":391.2584533691406,"yPoint":1906.122314453125,"shapeBezChanged":false}},{"xPoint":391.2584533691406,"yPoint":1856.119873046875,"shapeBezChanged":false,"shapeVertBezPrev":{"xPoint":391.2584533691406,"yPoint":1881.1173095703125,"shapeBezChanged":false},"shapeVertBezNext":{"xPoint":366.92767333984375,"yPoint":1856.119873046875,"shapeBezChanged":false}},{"xPoint":318.25848388671875,"yPoint":1856.119873046875,"shapeBezChanged":false,"shapeVertBezPrev":{"xPoint":342.58953857421875,"yPoint":1856.119873046875,"shapeBezChanged":false},"shapeVertBezNext":{"xPoint":318.25848388671875,"yPoint":1881.1173095703125,"shapeBezChanged":false}}],"shapeVerticesVer":1,"fillColor":"#FFC6C6C6","borderColor":"#FFC6C6C6","border":2,"joinType":1,"rotateAngle":0,"cornerRadius":16,"borderDash":0,"borderDashGap":0,"borderStyle":0,"shadow":{"shadowRadius":0,"shadowColor":"#FF444444","shadowDist":0,"shadowAngle":45}}],"flipHorizontal":1,"flipVertical":1},{"viewId":1607103914736,"layerFullLocked":false,"layerHidden":false,"layerLocked":"true","maskRoundRectRadius":0,"border":"0","borderColor":"#00000000","borderDash":0,"borderDashGap":0,"borderStyle":0,"opacity":"1.0","rotateAngle":"90.0","backgroundColor":"#00000000","xPoint":"0.0","yPoint":"0.0","selected":"false","tiltX":0,"tiltY":0,"layoutParamsHeight":"-1","layoutParamsWidth":"-1","rootLayoutHeight":"2000","rootLayoutWidth":"2000","textPadding":0,"viewType":"shapeView2","zoomScale":"0.7200001","shapeLayers":[{"shapeType":"shapePen","shapeVertices":[{"xPoint":356.86114501953125,"yPoint":1862.49462890625,"shapeBezChanged":false,"shapeVertBezNext":{"xPoint":357.22723388671875,"yPoint":1862.49462890625,"shapeBezChanged":false}},{"xPoint":357.95965576171875,"yPoint":1862.49462890625,"shapeBezChanged":false,"shapeVertBezPrev":{"xPoint":357.59344482421875,"yPoint":1862.49462890625,"shapeBezChanged":false},"shapeVertBezNext":{"xPoint":357.85882568359375,"yPoint":1877.73681640625,"shapeBezChanged":true}},{"xPoint":368.8611145019531,"yPoint":1894.4945068359375,"shapeBezChanged":false,"shapeVertBezPrev":{"xPoint":362.3724365234375,"yPoint":1886.9208984375,"shapeBezChanged":true},"shapeVertBezNext":{"xPoint":365.066650390625,"yPoint":1900.962890625,"shapeBezChanged":true}},{"xPoint":364.02490234375,"yPoint":1913.49462890625,"shapeBezChanged":false,"shapeVertBezPrev":{"xPoint":364.029052734375,"yPoint":1903.90625,"shapeBezChanged":true},"shapeVertBezNext":{"xPoint":361.63720703125,"yPoint":1913.49462890625,"shapeBezChanged":false}},{"xPoint":356.86114501953125,"yPoint":1913.49462890625,"shapeBezChanged":false,"shapeVertBezPrev":{"xPoint":359.24884033203125,"yPoint":1913.49462890625,"shapeBezChanged":false},"shapeVertBezNext":{"xPoint":356.86114501953125,"yPoint":1909.758544921875,"shapeBezChanged":false}},{"xPoint":356.86114501953125,"yPoint":1902.2857666015625,"shapeBezChanged":false,"shapeVertBezPrev":{"xPoint":356.86114501953125,"yPoint":1906.0216064453125,"shapeBezChanged":false},"shapeVertBezNext":{"xPoint":359.20574951171875,"yPoint":1901.831787109375,"shapeBezChanged":true}},{"xPoint":360.8729248046875,"yPoint":1896.9617919921875,"shapeBezChanged":false,"shapeVertBezPrev":{"xPoint":360.87176513671875,"yPoint":1899.8702392578125,"shapeBezChanged":true},"shapeVertBezNext":{"xPoint":361.0380859375,"yPoint":1894.0435791015625,"shapeBezChanged":true}},{"xPoint":356.86114501953125,"yPoint":1891.6375732421875,"shapeBezChanged":false,"shapeVertBezPrev":{"xPoint":359.10980224609375,"yPoint":1891.8319091796875,"shapeBezChanged":true},"shapeVertBezNext":{"xPoint":356.86114501953125,"yPoint":1881.92431640625,"shapeBezChanged":false}},{"xPoint":356.86114501953125,"yPoint":1862.49462890625,"shapeBezChanged":false,"shapeVertBezPrev":{"xPoint":356.86114501953125,"yPoint":1872.2078857421875,"shapeBezChanged":false}}],"shapeVerticesVer":1,"fillColor":"#FF000000","borderColor":"#EB000000","border":0,"joinType":1,"rotateAngle":0,"cornerRadius":0,"borderDash":0,"borderDashGap":0,"borderStyle":0,"shadow":{"shadowRadius":0,"shadowColor":"#FF444444","shadowDist":0,"shadowAngle":45}}],"flipHorizontal":1,"flipVertical":1},{"viewId":1607104566042,"layerFullLocked":false,"layerHidden":false,"layerLocked":"true","maskRoundRectRadius":0,"border":"0","borderColor":"#00000000","borderDash":0,"borderDashGap":0,"borderStyle":0,"opacity":"1.0","rotateAngle":"90.0","backgroundColor":"#00000000","xPoint":"0.0","yPoint":"0.0","selected":"false","tiltX":0,"tiltY":0,"layoutParamsHeight":"-1","layoutParamsWidth":"-1","rootLayoutHeight":"2000","rootLayoutWidth":"2000","textPadding":0,"viewType":"shapeView2","zoomScale":"0.7200001","shapeLayers":[{"shapeType":"shapePen","shapeVertices":[{"xPoint":353.632568359375,"yPoint":1862.49462890625,"shapeBezChanged":false,"shapeVertBezNext":{"xPoint":353.266357421875,"yPoint":1862.49462890625,"shapeBezChanged":false}},{"xPoint":352.53411865234375,"yPoint":1862.49462890625,"shapeBezChanged":false,"shapeVertBezPrev":{"xPoint":352.900146484375,"yPoint":1862.49462890625,"shapeBezChanged":false},"shapeVertBezNext":{"xPoint":352.63482666015625,"yPoint":1877.73681640625,"shapeBezChanged":true}},{"xPoint":341.632568359375,"yPoint":1894.4945068359375,"shapeBezChanged":false,"shapeVertBezPrev":{"xPoint":348.1212158203125,"yPoint":1886.9208984375,"shapeBezChanged":true},"shapeVertBezNext":{"xPoint":345.42706298828125,"yPoint":1900.962890625,"shapeBezChanged":true}},{"xPoint":346.46868896484375,"yPoint":1913.49462890625,"shapeBezChanged":false,"shapeVertBezPrev":{"xPoint":346.46466064453125,"yPoint":1903.90625,"shapeBezChanged":true},"shapeVertBezNext":{"xPoint":348.85638427734375,"yPoint":1913.49462890625,"shapeBezChanged":false}},{"xPoint":353.632568359375,"yPoint":1913.49462890625,"shapeBezChanged":false,"shapeVertBezPrev":{"xPoint":351.24481201171875,"yPoint":1913.49462890625,"shapeBezChanged":false},"shapeVertBezNext":{"xPoint":353.632568359375,"yPoint":1909.758544921875,"shapeBezChanged":false}},{"xPoint":353.632568359375,"yPoint":1902.2857666015625,"shapeBezChanged":false,"shapeVertBezPrev":{"xPoint":353.632568359375,"yPoint":1906.0216064453125,"shapeBezChanged":false},"shapeVertBezNext":{"xPoint":351.28790283203125,"yPoint":1901.831787109375,"shapeBezChanged":true}},{"xPoint":349.6207275390625,"yPoint":1896.9617919921875,"shapeBezChanged":false,"shapeVertBezPrev":{"xPoint":349.621826171875,"yPoint":1899.8702392578125,"shapeBezChanged":true},"shapeVertBezNext":{"xPoint":349.45556640625,"yPoint":1894.0435791015625,"shapeBezChanged":true}},{"xPoint":353.632568359375,"yPoint":1891.6375732421875,"shapeBezChanged":false,"shapeVertBezPrev":{"xPoint":351.38397216796875,"yPoint":1891.8319091796875,"shapeBezChanged":true},"shapeVertBezNext":{"xPoint":353.632568359375,"yPoint":1881.92431640625,"shapeBezChanged":false}},{"xPoint":353.632568359375,"yPoint":1862.49462890625,"shapeBezChanged":false,"shapeVertBezPrev":{"xPoint":353.632568359375,"yPoint":1872.2078857421875,"shapeBezChanged":false}}],"shapeVerticesVer":1,"fillColor":"#FF000000","borderColor":"#EB000000","border":0,"joinType":1,"rotateAngle":0,"cornerRadius":0,"borderDash":0,"borderDashGap":0,"borderStyle":0,"shadow":{"shadowRadius":0,"shadowColor":"#FF444444","shadowDist":0,"shadowAngle":45}}],"flipHorizontal":1,"flipVertical":1},{"viewId":1607104600773,"layerFullLocked":false,"layerHidden":false,"layerLocked":"true","maskRoundRectRadius":0,"border":"0","borderColor":"#00000000","borderDash":0,"borderDashGap":0,"borderStyle":0,"opacity":"1.0","rotateAngle":"90.0","backgroundColor":"#00000000","xPoint":"0.0","yPoint":"0.0","selected":"false","tiltX":0,"tiltY":0,"layoutParamsHeight":"-1","layoutParamsWidth":"-1","rootLayoutHeight":"2000","rootLayoutWidth":"2000","textPadding":0,"viewType":"shapeView2","zoomScale":"0.7200001","shapeLayers":[{"shapeType":"shapePolygon","shapeVertices":[{"xPoint":347.299072265625,"yPoint":1924.68017578125,"shapeBezChanged":false,"shapeVertBezPrev":{"xPoint":347.299072265625,"yPoint":1922.013671875,"shapeBezChanged":false},"shapeVertBezNext":{"xPoint":352.2987060546875,"yPoint":1924.68017578125,"shapeBezChanged":false}},{"xPoint":362.299072265625,"yPoint":1924.68017578125,"shapeBezChanged":false,"shapeVertBezPrev":{"xPoint":357.29949951171875,"yPoint":1924.68017578125,"shapeBezChanged":false},"shapeVertBezNext":{"xPoint":362.299072265625,"yPoint":1922.013671875,"shapeBezChanged":false}},{"xPoint":362.299072265625,"yPoint":1916.68017578125,"shapeBezChanged":false,"shapeVertBezPrev":{"xPoint":362.299072265625,"yPoint":1919.3466796875,"shapeBezChanged":false},"shapeVertBezNext":{"xPoint":357.29949951171875,"yPoint":1916.68017578125,"shapeBezChanged":false}},{"xPoint":347.299072265625,"yPoint":1916.68017578125,"shapeBezChanged":false,"shapeVertBezPrev":{"xPoint":352.2987060546875,"yPoint":1916.68017578125,"shapeBezChanged":false},"shapeVertBezNext":{"xPoint":347.299072265625,"yPoint":1919.3466796875,"shapeBezChanged":false}}],"shapeVerticesVer":1,"fillColor":"#FF000000","borderColor":"#FF000000","border":0,"joinType":1,"rotateAngle":0,"cornerRadius":0,"borderDash":0,"borderDashGap":0,"borderStyle":0,"shadow":{"shadowRadius":0,"shadowColor":"#FF444444","shadowDist":0,"shadowAngle":45}}],"flipHorizontal":1,"flipVertical":1},{"viewId":1648323190016,"layerFullLocked":false,"layerHidden":false,"layerLocked":"false","maskRoundRectRadius":16,"border":"0","borderColor":"#00000000","borderDash":0,"borderDashGap":0,"borderStyle":0,"opacity":"1.0","rotateAngle":"90.0","backgroundColor":"#00000000","xPoint":"318.25848","yPoint":"1856.1199","selected":"false","tiltX":0,"tiltY":0,"layoutParamsHeight":"-2","layoutParamsWidth":"-2","rootLayoutHeight":"75","rootLayoutWidth":"72","textPadding":0,"viewType":"groupView","groupChildIds":[{"viewId":1615547862965,"groupChildProps":{"xPoint":318.25848388671875,"yPoint":1856.119873046875,"width":72,"height":75,"border":2,"maskRoundRectRadius":16,"textPadding":0,"shadowRadius":0,"cornerRadius":16,"shadowDist":0}},{"viewId":1607103914736,"groupChildProps":{"xPoint":356.86114501953125,"yPoint":1862.49462890625,"width":11,"height":51,"border":0,"maskRoundRectRadius":0,"textPadding":0,"shadowRadius":0,"cornerRadius":0,"shadowDist":0}},{"viewId":1607104566042,"groupChildProps":{"xPoint":341.632568359375,"yPoint":1862.49462890625,"width":12,"height":51,"border":0,"maskRoundRectRadius":0,"textPadding":0,"shadowRadius":0,"cornerRadius":0,"shadowDist":0}},{"viewId":1607104600773,"groupChildProps":{"xPoint":347.299072265625,"yPoint":1916.68017578125,"width":15,"height":8,"border":0,"maskRoundRectRadius":0,"textPadding":0,"shadowRadius":0,"cornerRadius":0,"shadowDist":0}},{"viewId":1648323190016,"groupChildProps":{"xPoint":318.25848388671875,"yPoint":1856.119873046875,"width":72,"height":75,"border":0,"maskRoundRectRadius":0,"textPadding":-1}}]}],"project_files":[".images\/1648218458267.imagitorImage",".images\/1648219421085.imagitorImage",".images\/1648219771627.imagitorImage"],"project_description":"آج کی حدیث27________مارچ202222________شعبان1443ہفتہرسول اکرم ﷺ نے فرمایامسلمانوں کو جو پریشانی غم ،رنج ، تکلیف اور دکھ پہنچتا ہے حتٰی کہ اگر اس کو کوئی کانٹا بھی چبھتا ہے تو اللہ تعالی اس تکلیف کو اس کے گناہوں کا کفارہ بنادیتا ہے۔صحیح بخاری (5641)IMAGITORÎÖÍ"}